entrega/simulation/generated/bcd_7seg.v
// Copyright (C) 2021  Intel Corporation. All rights reserved.
// Your use of Intel Corporation's design tools, logic functions 
// and other software and tools, and any partner logic 
// functions, and any output files from any of the foregoing 
// (including device programming or simulation files), and any 
// associated documentation or information are expressly subject 
// to the terms and conditions of the Intel Program License 
// Subscription Agreement, the Intel Quartus Prime License Agreement,
// the Intel FPGA IP License Agreement, or other applicable license
// agreement, including, without limitation, that your use is for
// the sole purpose of programming logic devices manufactured by
// Intel and sold by Intel or its authorized distributors.  Please
// refer to the applicable agreement for further details, at
// https://fpgasoftware.intel.com/eula.


module bcd_7seg(
	BCD,
	SEG
);


input wire	[3:0] BCD;
output wire	[6:0] SEG;

wire	NBCD0;
wire	NBCD1;
wire	NBCD2;
wire	NBCD3;
wire	OR_D_FIRST;
wire	P_0001;
wire	P_000x;
wire	P_00x1;
wire	P_11xx;
wire	P_1x1x;
wire	P_x010;
wire	P_x01x;
wire	P_x100;
wire	P_x101;
wire	P_x10x;
wire	P_x110;
wire	P_x111;
wire	P_xx11;
wire	[6:0] SEG_ALTERA_SYNTHESIZED;




assign	NBCD0 =  ~BCD[0];

assign	NBCD1 =  ~BCD[1];

assign	NBCD2 =  ~BCD[2];

assign	NBCD3 =  ~BCD[3];

assign	SEG_ALTERA_SYNTHESIZED[0] = P_x100 | P_1x1x | P_11xx | P_0001;

assign	SEG_ALTERA_SYNTHESIZED[1] = P_x101 | P_1x1x | P_11xx | P_x110;

assign	SEG_ALTERA_SYNTHESIZED[2] = P_1x1x | P_11xx | P_x010;

assign	OR_D_FIRST = P_x100 | P_0001 | P_1x1x | P_x111;

assign	SEG_ALTERA_SYNTHESIZED[3] = P_11xx | OR_D_FIRST;

assign	SEG_ALTERA_SYNTHESIZED[4] = P_x10x | P_1x1x | BCD[0];

assign	SEG_ALTERA_SYNTHESIZED[5] = P_xx11 | P_00x1 | P_11xx | P_x01x;

assign	SEG_ALTERA_SYNTHESIZED[6] = P_x111 | P_1x1x | P_11xx | P_000x;

assign	P_0001 = NBCD3 & NBCD2 & NBCD1 & BCD[0];

assign	P_000x = NBCD3 & NBCD2 & NBCD1;

assign	P_00x1 = NBCD3 & NBCD2 & BCD[0];

assign	P_11xx = BCD[3] & BCD[2];

assign	P_1x1x = BCD[3] & BCD[1];

assign	P_x010 = NBCD2 & BCD[1] & NBCD0;

assign	P_x01x = NBCD2 & BCD[1];

assign	P_x100 = BCD[2] & NBCD1 & NBCD0;

assign	P_x101 = BCD[2] & NBCD1 & BCD[0];

assign	P_x10x = BCD[2] & NBCD1;

assign	P_x110 = BCD[2] & BCD[1] & NBCD0;

assign	P_x111 = BCD[2] & BCD[1] & BCD[0];

assign	P_xx11 = BCD[1] & BCD[0];

assign	SEG = SEG_ALTERA_SYNTHESIZED;

endmodule

entrega/simulation/tb_bcd_7seg.sv
module tb_bcd_7seg;
    logic [3:0] BCD;
    wire [6:0] SEG;
    integer value;

    bcd_7seg dut (.BCD(BCD), .SEG(SEG));

    function automatic [6:0] expected_segments(input logic [3:0] digit);
        case (digit)
            4'd0: expected_segments = 7'b1000000;
            4'd1: expected_segments = 7'b1111001;
            4'd2: expected_segments = 7'b0100100;
            4'd3: expected_segments = 7'b0110000;
            4'd4: expected_segments = 7'b0011001;
            4'd5: expected_segments = 7'b0010010;
            4'd6: expected_segments = 7'b0000010;
            4'd7: expected_segments = 7'b1111000;
            4'd8: expected_segments = 7'b0000000;
            4'd9: expected_segments = 7'b0010000;
            default: expected_segments = 7'b1111111;
        endcase
    endfunction

    initial begin
        $dumpfile("waveforms/bcd_7seg.vcd");
        $dumpvars(0, tb_bcd_7seg);
        for (value = 0; value < 16; value = value + 1) begin
            BCD = value[3:0];
            #1;
            if (SEG !== expected_segments(BCD))
                $fatal(1, "bcd_7seg BCD=%0d SEG=%07b", value, SEG);
        end
        $display("tb_bcd_7seg passou em 16 vetores");
        $finish;
    end
endmodule

entrega/simulation/waveforms/bcd_7seg.vcd
$date
	Wed Sep 30 02:06:35 2026
$end
$version
	Icarus Verilog
$end
$timescale
	1s
$end
$scope module tb_bcd_7seg $end
$var wire 7 ! SEG [6:0] $end
$var reg 4 " BCD [3:0] $end
$var integer 32 # value [31:0] $end
$scope function expected_segments $end
$upscope $end
$scope module dut $end
$var wire 4 $ BCD [3:0] $end
$var wire 1 % NBCD0 $end
$var wire 1 & NBCD1 $end
$var wire 1 ' NBCD2 $end
$var wire 1 ( NBCD3 $end
$var wire 1 ) OR_D_FIRST $end
$var wire 1 * P_0001 $end
$var wire 1 + P_000x $end
$var wire 1 , P_00x1 $end
$var wire 1 - P_11xx $end
$var wire 1 . P_1x1x $end
$var wire 1 / P_x010 $end
$var wire 1 0 P_x01x $end
$var wire 1 1 P_x100 $end
$var wire 1 2 P_x101 $end
$var wire 1 3 P_x10x $end
$var wire 1 4 P_x110 $end
$var wire 1 5 P_x111 $end
$var wire 1 6 P_xx11 $end
$var wire 7 7 SEG [6:0] $end
$var wire 7 8 SEG_ALTERA_SYNTHESIZED [6:0] $end
$upscope $end
$upscope $end
$enddefinitions $end
$comment Show the parameter values. $end
$dumpall
$end
#0
$dumpvars
b1000000 8
b1000000 7
06
05
04
03
02
01
00
0/
0.
0-
0,
1+
0*
0)
1(
1'
1&
1%
b0 $
b0 #
b0 "
b1000000 !
$end
#1
1)
b1111001 !
b1111001 7
b1111001 8
0%
1*
1,
b1 "
b1 $
b1 #
#2
0)
b100100 !
b100100 7
b100100 8
0+
1/
1%
0&
0*
0,
10
b10 "
b10 $
b10 #
#3
b110000 !
b110000 7
b110000 8
0/
0%
1,
16
b11 "
b11 $
b11 #
#4
1)
b11001 !
b11001 7
b11001 8
11
13
1%
1&
0'
0,
00
06
b100 "
b100 $
b100 #
#5
b10010 !
b10010 7
b10010 8
0)
01
0%
12
b101 "
b101 $
b101 #
#6
b10 !
b10 7
b10 8
03
14
1%
0&
02
b110 "
b110 $
b110 #
#7
b1111000 !
b1111000 7
b1111000 8
04
1)
0%
15
16
b111 "
b111 $
b111 #
#8
b0 !
b0 7
b0 8
0)
1%
1&
1'
0(
05
06
b1000 "
b1000 $
b1000 #
#9
b10000 !
b10000 7
b10000 8
0%
b1001 "
b1001 $
b1001 #
#10
b1111111 !
b1111111 7
b1111111 8
1)
1/
1%
0&
1.
10
b1010 "
b1010 $
b1010 #
#11
0/
0%
16
b1011 "
b1011 $
b1011 #
#12
b1111111 !
b1111111 7
b1111111 8
1)
11
13
1%
1&
0'
1-
0.
00
06
b1100 "
b1100 $
b1100 #
#13
0)
01
0%
12
b1101 "
b1101 $
b1101 #
#14
1)
03
14
1%
0&
1.
02
b1110 "
b1110 $
b1110 #
#15
04
0%
15
16
b1111 "
b1111 $
b1111 #
#16
b10000 #
