entrega/simulation/generated/decodificador_operacao.v
// Copyright (C) 2021  Intel Corporation. All rights reserved.
// Your use of Intel Corporation's design tools, logic functions 
// and other software and tools, and any partner logic 
// functions, and any output files from any of the foregoing 
// (including device programming or simulation files), and any 
// associated documentation or information are expressly subject 
// to the terms and conditions of the Intel Program License 
// Subscription Agreement, the Intel Quartus Prime License Agreement,
// the Intel FPGA IP License Agreement, or other applicable license
// agreement, including, without limitation, that your use is for
// the sole purpose of programming logic devices manufactured by
// Intel and sold by Intel or its authorized distributors.  Please
// refer to the applicable agreement for further details, at
// https://fpgasoftware.intel.com/eula.


module decodificador_operacao(
	S,
	EXIBE_F,
	D
);


input wire	[2:0] S;
output wire	EXIBE_F;
output wire	[7:0] D;

wire	[7:0] D_ALTERA_SYNTHESIZED;
wire	NS_0;
wire	NS_1;
wire	NS_2;




assign	D_ALTERA_SYNTHESIZED[0] = NS_2 & NS_1 & NS_0;

assign	D_ALTERA_SYNTHESIZED[1] = NS_2 & NS_1 & S[0];

assign	D_ALTERA_SYNTHESIZED[2] = NS_2 & S[1] & NS_0;

assign	D_ALTERA_SYNTHESIZED[3] = NS_2 & S[1] & S[0];

assign	D_ALTERA_SYNTHESIZED[4] = S[2] & NS_1 & NS_0;

assign	D_ALTERA_SYNTHESIZED[5] = S[2] & NS_1 & S[0];

assign	D_ALTERA_SYNTHESIZED[6] = S[2] & S[1] & NS_0;

assign	D_ALTERA_SYNTHESIZED[7] = S[2] & S[1] & S[0];

assign	NS_0 =  ~S[0];

assign	NS_1 =  ~S[1];

assign	NS_2 =  ~S[2];

assign	EXIBE_F = NS_2 & NS_1;

assign	D = D_ALTERA_SYNTHESIZED;

endmodule

entrega/simulation/tb_decodificador_operacao.sv
module tb_decodificador_operacao;
logic [2:0] S;
wire [7:0] D;
wire EXIBE_F;
logic [7:0] expected_d;
integer si, tested;
decodificador_operacao dut(.S(S), .D(D), .EXIBE_F(EXIBE_F));
initial begin
    $dumpfile("waveforms/decodificador_operacao.vcd");
    $dumpvars(0, tb_decodificador_operacao);
    tested = 0;
    for (si = 0; si < 8; si = si + 1) begin
        S = si[2:0];
        expected_d = 8'b1 << si;
        #1;
        if (D !== expected_d || EXIBE_F !== (si < 2))
            $fatal(1, "S=%b D=%b expected=%b EXIBE_F=%b expected=%b", S, D, expected_d, EXIBE_F, (si < 2));
        tested = tested + 1;
    end
    $display("PASS decodificador_operacao: %0d seletores", tested);
    $finish;
end
endmodule

entrega/simulation/waveforms/decodificador_operacao.vcd
$date
	Wed Sep 30 02:06:34 2026
$end
$version
	Icarus Verilog
$end
$timescale
	1s
$end
$scope module tb_decodificador_operacao $end
$var wire 1 ! EXIBE_F $end
$var wire 8 " D [7:0] $end
$var reg 3 # S [2:0] $end
$var reg 8 $ expected_d [7:0] $end
$var integer 32 % si [31:0] $end
$var integer 32 & tested [31:0] $end
$scope module dut $end
$var wire 8 ' D [7:0] $end
$var wire 1 ! EXIBE_F $end
$var wire 1 ( NS_0 $end
$var wire 1 ) NS_1 $end
$var wire 1 * NS_2 $end
$var wire 3 + S [2:0] $end
$var wire 8 , D_ALTERA_SYNTHESIZED [7:0] $end
$upscope $end
$upscope $end
$enddefinitions $end
$comment Show the parameter values. $end
$dumpall
$end
#0
$dumpvars
b1 ,
b0 +
1*
1)
1(
b1 '
b0 &
b0 %
b1 $
b0 #
b1 "
1!
$end
#1
b10 "
b10 '
b10 ,
0(
b10 $
b1 #
b1 +
b1 %
b1 &
#2
b100 "
b100 '
b100 ,
0!
1(
0)
b100 $
b10 #
b10 +
b10 %
b10 &
#3
b1000 "
b1000 '
b1000 ,
0(
b1000 $
b11 #
b11 +
b11 %
b11 &
#4
b10000 "
b10000 '
b10000 ,
1(
1)
0*
b10000 $
b100 #
b100 +
b100 %
b100 &
#5
b100000 "
b100000 '
b100000 ,
0(
b100000 $
b101 #
b101 +
b101 %
b101 &
#6
b1000000 "
b1000000 '
b1000000 ,
1(
0)
b1000000 $
b110 #
b110 +
b110 %
b110 &
#7
b10000000 "
b10000000 '
b10000000 ,
0(
b10000000 $
b111 #
b111 +
b111 %
b111 &
#8
b1000 %
b1000 &
