entrega/simulation/generated/bcd_7seg.v
// Copyright (C) 2021  Intel Corporation. All rights reserved.
// Your use of Intel Corporation's design tools, logic functions 
// and other software and tools, and any partner logic 
// functions, and any output files from any of the foregoing 
// (including device programming or simulation files), and any 
// associated documentation or information are expressly subject 
// to the terms and conditions of the Intel Program License 
// Subscription Agreement, the Intel Quartus Prime License Agreement,
// the Intel FPGA IP License Agreement, or other applicable license
// agreement, including, without limitation, that your use is for
// the sole purpose of programming logic devices manufactured by
// Intel and sold by Intel or its authorized distributors.  Please
// refer to the applicable agreement for further details, at
// https://fpgasoftware.intel.com/eula.


module bcd_7seg(
	BCD,
	SEG
);


input wire	[3:0] BCD;
output wire	[6:0] SEG;

wire	NBCD0;
wire	NBCD1;
wire	NBCD2;
wire	NBCD3;
wire	OR_D_FIRST;
wire	P_0001;
wire	P_000x;
wire	P_00x1;
wire	P_11xx;
wire	P_1x1x;
wire	P_x010;
wire	P_x01x;
wire	P_x100;
wire	P_x101;
wire	P_x10x;
wire	P_x110;
wire	P_x111;
wire	P_xx11;
wire	[6:0] SEG_ALTERA_SYNTHESIZED;




assign	NBCD0 =  ~BCD[0];

assign	NBCD1 =  ~BCD[1];

assign	NBCD2 =  ~BCD[2];

assign	NBCD3 =  ~BCD[3];

assign	SEG_ALTERA_SYNTHESIZED[0] = P_x100 | P_1x1x | P_11xx | P_0001;

assign	SEG_ALTERA_SYNTHESIZED[1] = P_x101 | P_1x1x | P_11xx | P_x110;

assign	SEG_ALTERA_SYNTHESIZED[2] = P_1x1x | P_11xx | P_x010;

assign	OR_D_FIRST = P_x100 | P_0001 | P_1x1x | P_x111;

assign	SEG_ALTERA_SYNTHESIZED[3] = P_11xx | OR_D_FIRST;

assign	SEG_ALTERA_SYNTHESIZED[4] = P_x10x | P_1x1x | BCD[0];

assign	SEG_ALTERA_SYNTHESIZED[5] = P_xx11 | P_00x1 | P_11xx | P_x01x;

assign	SEG_ALTERA_SYNTHESIZED[6] = P_x111 | P_1x1x | P_11xx | P_000x;

assign	P_0001 = NBCD3 & NBCD2 & NBCD1 & BCD[0];

assign	P_000x = NBCD3 & NBCD2 & NBCD1;

assign	P_00x1 = NBCD3 & NBCD2 & BCD[0];

assign	P_11xx = BCD[3] & BCD[2];

assign	P_1x1x = BCD[3] & BCD[1];

assign	P_x010 = NBCD2 & BCD[1] & NBCD0;

assign	P_x01x = NBCD2 & BCD[1];

assign	P_x100 = BCD[2] & NBCD1 & NBCD0;

assign	P_x101 = BCD[2] & NBCD1 & BCD[0];

assign	P_x10x = BCD[2] & NBCD1;

assign	P_x110 = BCD[2] & BCD[1] & NBCD0;

assign	P_x111 = BCD[2] & BCD[1] & BCD[0];

assign	P_xx11 = BCD[1] & BCD[0];

assign	SEG = SEG_ALTERA_SYNTHESIZED;

endmodule

entrega/simulation/generated/somador_1bit.v
// Copyright (C) 2021  Intel Corporation. All rights reserved.
// Your use of Intel Corporation's design tools, logic functions 
// and other software and tools, and any partner logic 
// functions, and any output files from any of the foregoing 
// (including device programming or simulation files), and any 
// associated documentation or information are expressly subject 
// to the terms and conditions of the Intel Program License 
// Subscription Agreement, the Intel Quartus Prime License Agreement,
// the Intel FPGA IP License Agreement, or other applicable license
// agreement, including, without limitation, that your use is for
// the sole purpose of programming logic devices manufactured by
// Intel and sold by Intel or its authorized distributors.  Please
// refer to the applicable agreement for further details, at
// https://fpgasoftware.intel.com/eula.


module somador_1bit(
	A,
	B,
	Cin,
	S,
	Cout
);


input wire	A;
input wire	B;
input wire	Cin;
output wire	S;
output wire	Cout;

wire	fa_G;
wire	fa_H;
wire	fa_P;




assign	fa_G = A & B;

assign	fa_H = fa_P & Cin;

assign	Cout = fa_H | fa_G;

assign	fa_P = A ^ B;

assign	S = fa_P ^ Cin;


endmodule

entrega/simulation/generated/somador_subtrator_5bit.v
// Copyright (C) 2021  Intel Corporation. All rights reserved.
// Your use of Intel Corporation's design tools, logic functions 
// and other software and tools, and any partner logic 
// functions, and any output files from any of the foregoing 
// (including device programming or simulation files), and any 
// associated documentation or information are expressly subject 
// to the terms and conditions of the Intel Program License 
// Subscription Agreement, the Intel Quartus Prime License Agreement,
// the Intel FPGA IP License Agreement, or other applicable license
// agreement, including, without limitation, that your use is for
// the sole purpose of programming logic devices manufactured by
// Intel and sold by Intel or its authorized distributors.  Please
// refer to the applicable agreement for further details, at
// https://fpgasoftware.intel.com/eula.


module somador_subtrator_5bit(
	SUB,
	A,
	B,
	Cout,
	R
);


input wire	SUB;
input wire	[4:0] A;
input wire	[4:0] B;
output wire	Cout;
output wire	[4:0] R;

wire	[4:0] BX;
wire	[4:1] CARRY;
wire	[4:0] R_ALTERA_SYNTHESIZED;





somador_1bit	b2v_fa_0(
	.A(A[0]),
	.B(BX[0]),
	.Cin(SUB),
	.S(R_ALTERA_SYNTHESIZED[0]),
	.Cout(CARRY[1]));


somador_1bit	b2v_fa_1(
	.A(A[1]),
	.B(BX[1]),
	.Cin(CARRY[1]),
	.S(R_ALTERA_SYNTHESIZED[1]),
	.Cout(CARRY[2]));


somador_1bit	b2v_fa_2(
	.A(A[2]),
	.B(BX[2]),
	.Cin(CARRY[2]),
	.S(R_ALTERA_SYNTHESIZED[2]),
	.Cout(CARRY[3]));


somador_1bit	b2v_fa_3(
	.A(A[3]),
	.B(BX[3]),
	.Cin(CARRY[3]),
	.S(R_ALTERA_SYNTHESIZED[3]),
	.Cout(CARRY[4]));


somador_1bit	b2v_fa_4(
	.A(A[4]),
	.B(BX[4]),
	.Cin(CARRY[4]),
	.S(R_ALTERA_SYNTHESIZED[4]),
	.Cout(Cout));

assign	BX[0] = B[0] ^ SUB;

assign	BX[1] = B[1] ^ SUB;

assign	BX[2] = B[2] ^ SUB;

assign	BX[3] = B[3] ^ SUB;

assign	BX[4] = B[4] ^ SUB;

assign	R = R_ALTERA_SYNTHESIZED;

endmodule

entrega/simulation/generated/bin_bcd.v
// Copyright (C) 2021  Intel Corporation. All rights reserved.
// Your use of Intel Corporation's design tools, logic functions 
// and other software and tools, and any partner logic 
// functions, and any output files from any of the foregoing 
// (including device programming or simulation files), and any 
// associated documentation or information are expressly subject 
// to the terms and conditions of the Intel Program License 
// Subscription Agreement, the Intel Quartus Prime License Agreement,
// the Intel FPGA IP License Agreement, or other applicable license
// agreement, including, without limitation, that your use is for
// the sole purpose of programming logic devices manufactured by
// Intel and sold by Intel or its authorized distributors.  Please
// refer to the applicable agreement for further details, at
// https://fpgasoftware.intel.com/eula.


module bin_bcd(
	MAG,
	DEZ,
	UNI
);


input wire	[4:0] MAG;
output wire	[3:0] DEZ;
output wire	[3:0] UNI;

wire	A10_HI;
wire	buf_dez0__buffer_net;
wire	buf_dez1__buffer_net;
wire	correction_bit_1__buffer_net;
wire	correction_bit_2__buffer_net;
wire	correction_bit_3__buffer_net;
wire	correction_bit_4__buffer_net;
wire	COUT_UNUSED;
wire	DEZ0_A;
wire	DEZ0_INTERNAL;
wire	[3:0] DEZ_ALTERA_SYNTHESIZED;
wire	[4:0] K;
wire	NT20;
wire	O10_MID;
wire	O20_MID;
wire	SUB_ONE;
wire	T10;
wire	T20;
wire	T30;
wire	[3:0] UNI_ALTERA_SYNTHESIZED;
wire	[4:0] UNI_RAW;
wire	unit_bit_0__buffer_net;
wire	unit_bit_1__buffer_net;
wire	unit_bit_2__buffer_net;
wire	unit_bit_3__buffer_net;




assign	A10_HI = MAG[3] & O10_MID;

assign	T20 = MAG[4] & O20_MID;

assign	T30 = MAG[4] & MAG[3] & MAG[2] & MAG[1];

assign	DEZ0_A = T10 & NT20;

assign	buf_dez0__buffer_net =  ~DEZ0_INTERNAL;

assign	DEZ_ALTERA_SYNTHESIZED[0] =  ~buf_dez0__buffer_net;

assign	buf_dez1__buffer_net =  ~T20;

assign	DEZ_ALTERA_SYNTHESIZED[1] =  ~buf_dez1__buffer_net;

assign	correction_bit_1__buffer_net =  ~DEZ0_INTERNAL;

assign	K[1] =  ~correction_bit_1__buffer_net;

assign	correction_bit_2__buffer_net =  ~T20;

assign	K[2] =  ~correction_bit_2__buffer_net;

assign	correction_bit_3__buffer_net =  ~DEZ0_INTERNAL;

assign	K[3] =  ~correction_bit_3__buffer_net;

assign	correction_bit_4__buffer_net =  ~T20;

assign	K[4] =  ~correction_bit_4__buffer_net;




assign	NT20 =  ~T20;

assign	T10 = A10_HI | MAG[4];

assign	O10_MID = MAG[1] | MAG[2];

assign	O20_MID = MAG[2] | MAG[3];

assign	DEZ0_INTERNAL = T30 | DEZ0_A;



somador_subtrator_5bit	b2v_subtract_tens(
	.SUB(SUB_ONE),
	.A(MAG),
	.B(K),
	
	.R(UNI_RAW));

assign	unit_bit_0__buffer_net =  ~UNI_RAW[0];

assign	UNI_ALTERA_SYNTHESIZED[0] =  ~unit_bit_0__buffer_net;

assign	unit_bit_1__buffer_net =  ~UNI_RAW[1];

assign	UNI_ALTERA_SYNTHESIZED[1] =  ~unit_bit_1__buffer_net;

assign	unit_bit_2__buffer_net =  ~UNI_RAW[2];

assign	UNI_ALTERA_SYNTHESIZED[2] =  ~unit_bit_2__buffer_net;

assign	unit_bit_3__buffer_net =  ~UNI_RAW[3];

assign	UNI_ALTERA_SYNTHESIZED[3] =  ~unit_bit_3__buffer_net;

assign	DEZ = DEZ_ALTERA_SYNTHESIZED;
assign	UNI = UNI_ALTERA_SYNTHESIZED;
assign	DEZ_ALTERA_SYNTHESIZED[2] = 0;
assign	DEZ_ALTERA_SYNTHESIZED[3] = 0;
assign	K[0] = 0;
assign	SUB_ONE = 1;

endmodule

entrega/simulation/generated/display_decimal_2digitos.v
// Copyright (C) 2021  Intel Corporation. All rights reserved.
// Your use of Intel Corporation's design tools, logic functions 
// and other software and tools, and any partner logic 
// functions, and any output files from any of the foregoing 
// (including device programming or simulation files), and any 
// associated documentation or information are expressly subject 
// to the terms and conditions of the Intel Program License 
// Subscription Agreement, the Intel Quartus Prime License Agreement,
// the Intel FPGA IP License Agreement, or other applicable license
// agreement, including, without limitation, that your use is for
// the sole purpose of programming logic devices manufactured by
// Intel and sold by Intel or its authorized distributors.  Please
// refer to the applicable agreement for further details, at
// https://fpgasoftware.intel.com/eula.


module display_decimal_2digitos(
	ENABLE,
	MAG,
	DEZ_SEG,
	UNI_SEG
);


input wire	ENABLE;
input wire	[4:0] MAG;
output wire	[6:0] DEZ_SEG;
output wire	[6:0] UNI_SEG;

wire	[3:0] BCD_DEZ;
wire	[3:0] BCD_UNI;
wire	[6:0] DEZ_RAW;
wire	[6:0] DEZ_SEG_ALTERA_SYNTHESIZED;
wire	DISABLED;
wire	[6:0] UNI_RAW;
wire	[6:0] UNI_SEG_ALTERA_SYNTHESIZED;





bin_bcd	b2v_convert_mag(
	.MAG(MAG),
	.DEZ(BCD_DEZ),
	.UNI(BCD_UNI));


bcd_7seg	b2v_decode_dez(
	.BCD(BCD_DEZ),
	.SEG(DEZ_RAW));


bcd_7seg	b2v_decode_uni(
	.BCD(BCD_UNI),
	.SEG(UNI_RAW));

assign	DISABLED =  ~ENABLE;

assign	DEZ_SEG_ALTERA_SYNTHESIZED[0] = DISABLED | DEZ_RAW[0];

assign	DEZ_SEG_ALTERA_SYNTHESIZED[1] = DISABLED | DEZ_RAW[1];

assign	DEZ_SEG_ALTERA_SYNTHESIZED[2] = DISABLED | DEZ_RAW[2];

assign	DEZ_SEG_ALTERA_SYNTHESIZED[3] = DISABLED | DEZ_RAW[3];

assign	DEZ_SEG_ALTERA_SYNTHESIZED[4] = DISABLED | DEZ_RAW[4];

assign	DEZ_SEG_ALTERA_SYNTHESIZED[5] = DISABLED | DEZ_RAW[5];

assign	DEZ_SEG_ALTERA_SYNTHESIZED[6] = DISABLED | DEZ_RAW[6];

assign	UNI_SEG_ALTERA_SYNTHESIZED[0] = DISABLED | UNI_RAW[0];

assign	UNI_SEG_ALTERA_SYNTHESIZED[1] = DISABLED | UNI_RAW[1];

assign	UNI_SEG_ALTERA_SYNTHESIZED[2] = DISABLED | UNI_RAW[2];

assign	UNI_SEG_ALTERA_SYNTHESIZED[3] = DISABLED | UNI_RAW[3];

assign	UNI_SEG_ALTERA_SYNTHESIZED[4] = DISABLED | UNI_RAW[4];

assign	UNI_SEG_ALTERA_SYNTHESIZED[5] = DISABLED | UNI_RAW[5];

assign	UNI_SEG_ALTERA_SYNTHESIZED[6] = DISABLED | UNI_RAW[6];

assign	DEZ_SEG = DEZ_SEG_ALTERA_SYNTHESIZED;
assign	UNI_SEG = UNI_SEG_ALTERA_SYNTHESIZED;

endmodule

entrega/simulation/tb_display_decimal_2digitos.sv
module tb_display_decimal_2digitos;
    logic [4:0] MAG;
    logic ENABLE;
    wire [6:0] DEZ_SEG;
    wire [6:0] UNI_SEG;
    integer value;
    integer enable_value;
    reg [6:0] expected_dez;
    reg [6:0] expected_uni;

    display_decimal_2digitos dut (.MAG(MAG), .ENABLE(ENABLE), .DEZ_SEG(DEZ_SEG), .UNI_SEG(UNI_SEG));

    function automatic [6:0] expected_segments(input integer digit);
        case (digit)
            0: expected_segments = 7'b1000000;
            1: expected_segments = 7'b1111001;
            2: expected_segments = 7'b0100100;
            3: expected_segments = 7'b0110000;
            4: expected_segments = 7'b0011001;
            5: expected_segments = 7'b0010010;
            6: expected_segments = 7'b0000010;
            7: expected_segments = 7'b1111000;
            8: expected_segments = 7'b0000000;
            9: expected_segments = 7'b0010000;
            default: expected_segments = 7'b1111111;
        endcase
    endfunction

    initial begin
        $dumpfile("waveforms/display_decimal_2digitos.vcd");
        $dumpvars(0, tb_display_decimal_2digitos);
        for (enable_value = 0; enable_value < 2; enable_value = enable_value + 1) begin
            ENABLE = enable_value[0];
            for (value = 0; value < 32; value = value + 1) begin
                MAG = value[4:0];
                expected_dez = ENABLE ? expected_segments(value / 10) : 7'b1111111;
                expected_uni = ENABLE ? expected_segments(value % 10) : 7'b1111111;
                #1;
                if (DEZ_SEG !== expected_dez || UNI_SEG !== expected_uni)
                    $fatal(1, "display MAG=%0d ENABLE=%b DEZ=%07b UNI=%07b", value, ENABLE, DEZ_SEG, UNI_SEG);
            end
        end
        $display("tb_display_decimal_2digitos passou em 64 vetores");
        $finish;
    end
endmodule

entrega/simulation/waveforms/display_decimal_2digitos.vcd
$date
	Wed Sep 30 02:06:35 2026
$end
$version
	Icarus Verilog
$end
$timescale
	1s
$end
$scope module tb_display_decimal_2digitos $end
$var wire 7 ! UNI_SEG [6:0] $end
$var wire 7 " DEZ_SEG [6:0] $end
$var reg 1 # ENABLE $end
$var reg 5 $ MAG [4:0] $end
$var reg 7 % expected_dez [6:0] $end
$var reg 7 & expected_uni [6:0] $end
$var integer 32 ' enable_value [31:0] $end
$var integer 32 ( value [31:0] $end
$scope function expected_segments $end
$upscope $end
$scope module dut $end
$var wire 7 ) DEZ_SEG [6:0] $end
$var wire 1 * DISABLED $end
$var wire 1 # ENABLE $end
$var wire 5 + MAG [4:0] $end
$var wire 7 , UNI_SEG [6:0] $end
$var wire 7 - UNI_SEG_ALTERA_SYNTHESIZED [6:0] $end
$var wire 7 . UNI_RAW [6:0] $end
$var wire 7 / DEZ_SEG_ALTERA_SYNTHESIZED [6:0] $end
$var wire 7 0 DEZ_RAW [6:0] $end
$var wire 4 1 BCD_UNI [3:0] $end
$var wire 4 2 BCD_DEZ [3:0] $end
$scope module b2v_convert_mag $end
$var wire 1 3 A10_HI $end
$var wire 4 4 DEZ [3:0] $end
$var wire 1 5 DEZ0_A $end
$var wire 1 6 DEZ0_INTERNAL $end
$var wire 5 7 MAG [4:0] $end
$var wire 1 8 NT20 $end
$var wire 1 9 O10_MID $end
$var wire 1 : O20_MID $end
$var wire 1 ; SUB_ONE $end
$var wire 1 < T10 $end
$var wire 1 = T20 $end
$var wire 1 > T30 $end
$var wire 4 ? UNI [3:0] $end
$var wire 1 @ buf_dez0__buffer_net $end
$var wire 1 A buf_dez1__buffer_net $end
$var wire 1 B correction_bit_1__buffer_net $end
$var wire 1 C correction_bit_2__buffer_net $end
$var wire 1 D correction_bit_3__buffer_net $end
$var wire 1 E correction_bit_4__buffer_net $end
$var wire 1 F unit_bit_0__buffer_net $end
$var wire 1 G unit_bit_1__buffer_net $end
$var wire 1 H unit_bit_2__buffer_net $end
$var wire 1 I unit_bit_3__buffer_net $end
$var wire 5 J UNI_RAW [4:0] $end
$var wire 4 K UNI_ALTERA_SYNTHESIZED [3:0] $end
$var wire 5 L K [4:0] $end
$var wire 4 M DEZ_ALTERA_SYNTHESIZED [3:0] $end
$scope module b2v_subtract_tens $end
$var wire 5 N A [4:0] $end
$var wire 5 O B [4:0] $end
$var wire 5 P R [4:0] $end
$var wire 1 ; SUB $end
$var wire 5 Q R_ALTERA_SYNTHESIZED [4:0] $end
$var wire 1 R Cout $end
$var wire 4 S CARRY [4:1] $end
$var wire 5 T BX [4:0] $end
$scope module b2v_fa_0 $end
$var wire 1 U A $end
$var wire 1 V B $end
$var wire 1 ; Cin $end
$var wire 1 W Cout $end
$var wire 1 X S $end
$var wire 1 Y fa_G $end
$var wire 1 Z fa_H $end
$var wire 1 [ fa_P $end
$upscope $end
$scope module b2v_fa_1 $end
$var wire 1 \ A $end
$var wire 1 ] B $end
$var wire 1 ^ Cin $end
$var wire 1 _ Cout $end
$var wire 1 ` S $end
$var wire 1 a fa_G $end
$var wire 1 b fa_H $end
$var wire 1 c fa_P $end
$upscope $end
$scope module b2v_fa_2 $end
$var wire 1 d A $end
$var wire 1 e B $end
$var wire 1 f Cin $end
$var wire 1 g Cout $end
$var wire 1 h S $end
$var wire 1 i fa_G $end
$var wire 1 j fa_H $end
$var wire 1 k fa_P $end
$upscope $end
$scope module b2v_fa_3 $end
$var wire 1 l A $end
$var wire 1 m B $end
$var wire 1 n Cin $end
$var wire 1 o Cout $end
$var wire 1 p S $end
$var wire 1 q fa_G $end
$var wire 1 r fa_H $end
$var wire 1 s fa_P $end
$upscope $end
$scope module b2v_fa_4 $end
$var wire 1 t A $end
$var wire 1 u B $end
$var wire 1 v Cin $end
$var wire 1 R Cout $end
$var wire 1 w S $end
$var wire 1 x fa_G $end
$var wire 1 y fa_H $end
$var wire 1 z fa_P $end
$upscope $end
$upscope $end
$upscope $end
$scope module b2v_decode_dez $end
$var wire 4 { BCD [3:0] $end
$var wire 1 | NBCD0 $end
$var wire 1 } NBCD1 $end
$var wire 1 ~ NBCD2 $end
$var wire 1 !" NBCD3 $end
$var wire 1 "" OR_D_FIRST $end
$var wire 1 #" P_0001 $end
$var wire 1 $" P_000x $end
$var wire 1 %" P_00x1 $end
$var wire 1 &" P_11xx $end
$var wire 1 '" P_1x1x $end
$var wire 1 (" P_x010 $end
$var wire 1 )" P_x01x $end
$var wire 1 *" P_x100 $end
$var wire 1 +" P_x101 $end
$var wire 1 ," P_x10x $end
$var wire 1 -" P_x110 $end
$var wire 1 ." P_x111 $end
$var wire 1 /" P_xx11 $end
$var wire 7 0" SEG [6:0] $end
$var wire 7 1" SEG_ALTERA_SYNTHESIZED [6:0] $end
$upscope $end
$scope module b2v_decode_uni $end
$var wire 4 2" BCD [3:0] $end
$var wire 1 3" NBCD0 $end
$var wire 1 4" NBCD1 $end
$var wire 1 5" NBCD2 $end
$var wire 1 6" NBCD3 $end
$var wire 1 7" OR_D_FIRST $end
$var wire 1 8" P_0001 $end
$var wire 1 9" P_000x $end
$var wire 1 :" P_00x1 $end
$var wire 1 ;" P_11xx $end
$var wire 1 <" P_1x1x $end
$var wire 1 =" P_x010 $end
$var wire 1 >" P_x01x $end
$var wire 1 ?" P_x100 $end
$var wire 1 @" P_x101 $end
$var wire 1 A" P_x10x $end
$var wire 1 B" P_x110 $end
$var wire 1 C" P_x111 $end
$var wire 1 D" P_xx11 $end
$var wire 7 E" SEG [6:0] $end
$var wire 7 F" SEG_ALTERA_SYNTHESIZED [6:0] $end
$upscope $end
$upscope $end
$upscope $end
$enddefinitions $end
$comment Show the parameter values. $end
$dumpall
$end
#0
$dumpvars
b1000000 F"
b1000000 E"
0D"
0C"
0B"
0A"
0@"
0?"
0>"
0="
0<"
0;"
0:"
19"
08"
07"
16"
15"
14"
13"
b0 2"
b1000000 1"
b1000000 0"
0/"
0."
0-"
0,"
0+"
0*"
0)"
0("
0'"
0&"
0%"
1$"
0#"
0""
1!"
1~
1}
1|
b0 {
1z
1y
0x
0w
1v
1u
0t
1s
1r
0q
0p
1o
1n
1m
0l
1k
1j
0i
0h
1g
1f
1e
0d
1c
1b
0a
0`
1_
1^
1]
0\
1[
1Z
0Y
0X
1W
1V
0U
b11111 T
b1111 S
1R
b0 Q
b0 P
b0 O
b0 N
b0 M
b0 L
b0 K
b0 J
1I
1H
1G
1F
1E
1D
1C
1B
1A
1@
b0 ?
0>
0=
0<
1;
0:
09
18
b0 7
06
05
b0 4
03
b0 2
b0 1
b1000000 0
b1111111 /
b1000000 .
b1111111 -
b1111111 ,
b0 +
1*
b1111111 )
b0 (
b0 '
b1111111 &
b1111111 %
b0 $
0#
b1111111 "
b1111111 !
$end
#1
17"
b1111001 .
b1111001 E"
b1111001 F"
03"
18"
1:"
b1 1
b1 ?
b1 2"
b1 K
0F
b1 J
b1 P
b1 Q
1X
0Z
1Y
0[
1U
b1 $
b1 +
b1 7
b1 N
b1 (
#2
07"
b100100 .
b100100 E"
b100100 F"
09"
1="
13"
04"
08"
0:"
1>"
b10 1
b10 ?
b10 2"
b10 K
0G
1F
b10 J
b10 P
b10 Q
0X
1Z
1`
0b
19
0Y
1[
1a
0c
0U
1\
b10 $
b10 +
b10 7
b10 N
b10 (
#3
b110000 .
b110000 E"
b110000 F"
0="
03"
1:"
1D"
b11 1
b11 ?
b11 2"
b11 K
0F
b11 J
b11 P
b11 Q
1X
0Z
1Y
0[
1U
b11 $
b11 +
b11 7
b11 N
b11 (
#4
17"
b11001 .
b11001 E"
b11001 F"
1?"
1A"
13"
14"
05"
0:"
0>"
0D"
b100 1
b100 ?
b100 2"
b100 K
0H
1G
1F
b100 J
b100 P
b100 Q
0X
1Z
0`
1b
1h
0j
1:
0Y
1[
0a
1c
1i
0k
0U
0\
1d
b100 $
b100 +
b100 7
b100 N
b100 (
#5
b10010 .
b10010 E"
b10010 F"
07"
0?"
03"
1@"
b101 1
b101 ?
b101 2"
b101 K
0F
b101 J
b101 P
b101 Q
1X
0Z
1Y
0[
1U
b101 $
b101 +
b101 7
b101 N
b101 (
#6
b10 .
b10 E"
b10 F"
0A"
1B"
13"
04"
0@"
b110 1
b110 ?
b110 2"
b110 K
0G
1F
b110 J
b110 P
b110 Q
0X
1Z
1`
0b
0Y
1[
1a
0c
0U
1\
b110 $
b110 +
b110 7
b110 N
b110 (
#7
b1111000 .
b1111000 E"
b1111000 F"
0B"
17"
03"
1C"
1D"
b111 1
b111 ?
b111 2"
b111 K
0F
b111 J
b111 P
b111 Q
1X
0Z
1Y
0[
1U
b111 $
b111 +
b111 7
b111 N
b111 (
#8
b0 .
b0 E"
b0 F"
07"
13"
14"
15"
06"
0C"
0D"
b1000 1
b1000 ?
b1000 2"
b1000 K
0I
1H
1G
1F
b1000 J
b1000 P
b1000 Q
0X
1Z
0`
1b
0h
1j
1p
0r
09
0Y
1[
0a
1c
0i
1k
1q
0s
0U
0\
0d
1l
b1000 $
b1000 +
b1000 7
b1000 N
b1000 (
#9
b10000 .
b10000 E"
b10000 F"
03"
b1001 1
b1001 ?
b1001 2"
b1001 K
0F
b1001 J
b1001 P
b1001 Q
1X
0Z
1Y
0[
1U
b1001 $
b1001 +
b1001 7
b1001 N
b1001 (
#10
19"
16"
1I
0p
1r
0q
1s
0m
0]
b10101 T
1""
b1111001 0
b1111001 0"
b1111001 1"
b1000000 .
b1000000 E"
b1000000 F"
07"
0="
0|
1#"
1%"
13"
14"
0<"
0>"
b1010 L
b1010 O
b1 2
b1 4
b1 {
b1 M
b0 1
b0 ?
b0 2"
b0 K
0D
0B
0@
1G
1F
16
15
b0 J
b0 P
b0 Q
1<
13
0X
1Z
0`
1b
19
0Y
1[
0a
1c
0U
1\
b1010 $
b1010 +
b1010 7
b1010 N
b1010 (
#11
17"
b1111001 .
b1111001 E"
b1111001 F"
03"
18"
1:"
b1 1
b1 ?
b1 2"
b1 K
0F
b1 J
b1 P
b1 Q
1X
0Z
1Y
0[
1U
b1011 $
b1011 +
b1011 7
b1011 N
b1011 (
#12
07"
b100100 .
b100100 E"
b100100 F"
09"
1="
0?"
0B"
13"
04"
15"
08"
0:"
1>"
0A"
b10 1
b10 ?
b10 2"
b10 K
1H
0G
1F
0f
b1101 S
b10 J
b10 P
b10 Q
0_
0X
1Z
1`
0b
0h
0j
0Y
1[
0c
1i
0k
0U
0\
1d
b1100 $
b1100 +
b1100 7
b1100 N
b1100 (
#13
b110000 .
b110000 E"
b110000 F"
0="
03"
1:"
1D"
b11 1
b11 ?
b11 2"
b11 K
0F
b11 J
b11 P
b11 Q
1X
0Z
1Y
0[
1U
b1101 $
b1101 +
b1101 7
b1101 N
b1101 (
#14
17"
1?"
05"
1A"
b11001 .
b11001 E"
b11001 F"
09"
13"
14"
0:"
0>"
0D"
0H
b100 1
b100 ?
b100 2"
b100 K
1G
1F
1h
1f
b100 J
b100 P
b100 Q
b1111 S
1_
0X
1Z
0`
1b
0Y
1[
1c
0U
1\
b1110 $
b1110 +
b1110 7
b1110 N
b1110 (
#15
b10010 .
b10010 E"
b10010 F"
07"
0?"
03"
1@"
b101 1
b101 ?
b101 2"
b101 K
0F
b101 J
b101 P
b101 Q
1X
0Z
1Y
0[
1U
b1111 $
b1111 +
b1111 7
b1111 N
b1111 (
#16
1B"
0;"
b10 .
b10 E"
b10 F"
07"
0="
0>"
13"
04"
05"
16"
0<"
0@"
0A"
0n
b110 1
b110 ?
b110 2"
b110 K
0g
1I
0H
0G
1F
0v
0f
b1 S
b110 J
b110 P
b110 Q
0_
0o
0X
1Z
1`
0b
1h
0j
0p
0r
0w
0y
03
09
0:
0Y
1[
0c
0i
1k
0s
1x
0z
0U
0\
0d
0l
1t
b10000 $
b10000 +
b10000 7
b10000 N
b10000 (
#17
b1111000 .
b1111000 E"
b1111000 F"
0B"
17"
03"
1C"
1D"
b111 1
b111 ?
b111 2"
b111 K
0F
b111 J
b111 P
b111 Q
1X
0Z
1Y
0[
1U
b10001 $
b10001 +
b10001 7
b10001 N
b10001 (
#18
06"
09"
0I
15"
b0 .
b0 E"
b0 F"
0?"
0A"
07"
13"
14"
0C"
0D"
1p
1H
1n
b1000 1
b1000 ?
b1000 2"
b1000 K
1g
1G
1F
1j
0h
1f
b1000 J
b1000 P
b1000 Q
b111 S
1_
0X
1Z
0`
1b
19
0Y
1[
1c
0U
1\
b10010 $
b10010 +
b10010 7
b10010 N
b10010 (
#19
b10000 .
b10000 E"
b10000 F"
03"
b1001 1
b1001 ?
b1001 2"
b1001 K
0F
b1001 J
b1001 P
b1001 Q
1X
0Z
1Y
0[
1U
b10011 $
b10011 +
b10011 7
b10011 N
b10011 (
#20
19"
16"
1y
1I
1v
1o
1r
0p
1n
1s
1m
1]
1R
0w
1g
0""
0x
1z
b1000000 .
b1000000 E"
b1000000 F"
07"
b100100 0
b100100 0"
b100100 1"
0u
0e
1("
0="
0?"
0B"
b1011 T
1|
0%"
13"
14"
15"
0;"
0<"
0>"
0A"
0#"
0$"
b0 1
b0 ?
b0 2"
b0 K
0}
1)"
0/"
b10100 L
b10100 O
1D
1B
1@
1H
1G
1F
b10 2
b10 4
b10 {
b10 M
06
1f
05
b1111 S
b0 J
b0 P
b0 Q
0A
0C
0E
08
1_
1=
0X
1Z
0`
1b
0h
1j
1:
0Y
1[
1c
0i
1k
0U
0\
1d
b10100 $
b10100 +
b10100 7
b10100 N
b10100 (
#21
17"
b1111001 .
b1111001 E"
b1111001 F"
03"
18"
1:"
b1 1
b1 ?
b1 2"
b1 K
0F
b1 J
b1 P
b1 Q
1X
0Z
1Y
0[
1U
b10101 $
b10101 +
b10101 7
b10101 N
b10101 (
#22
07"
b100100 .
b100100 E"
b100100 F"
09"
1="
13"
04"
08"
0:"
1>"
b10 1
b10 ?
b10 2"
b10 K
0G
1F
b10 J
b10 P
b10 Q
0X
1Z
1`
0b
0Y
1[
1a
0c
0U
1\
b10110 $
b10110 +
b10110 7
b10110 N
b10110 (
#23
b110000 .
b110000 E"
b110000 F"
0="
03"
1:"
1D"
b11 1
b11 ?
b11 2"
b11 K
0F
b11 J
b11 P
b11 Q
1X
0Z
1Y
0[
1U
b10111 $
b10111 +
b10111 7
b10111 N
b10111 (
#24
17"
b11001 .
b11001 E"
b11001 F"
1?"
1A"
13"
14"
05"
16"
0:"
0;"
0>"
0D"
b100 1
b100 ?
b100 2"
b100 K
1I
0H
1G
1F
0n
b1011 S
b100 J
b100 P
b100 Q
0g
0X
1Z
0`
1b
1h
0j
0p
0r
09
0Y
1[
0a
1c
0k
1q
0s
0U
0\
0d
1l
b11000 $
b11000 +
b11000 7
b11000 N
b11000 (
#25
b10010 .
b10010 E"
b10010 F"
07"
0?"
03"
1@"
b101 1
b101 ?
b101 2"
b101 K
0F
b101 J
b101 P
b101 Q
1X
0Z
1Y
0[
1U
b11001 $
b11001 +
b11001 7
b11001 N
b11001 (
#26
b10 .
b10 E"
b10 F"
0A"
1B"
13"
04"
0@"
b110 1
b110 ?
b110 2"
b110 K
0G
1F
b110 J
b110 P
b110 Q
13
0X
1Z
1`
0b
19
0Y
1[
1a
0c
0U
1\
b11010 $
b11010 +
b11010 7
b11010 N
b11010 (
#27
b1111000 .
b1111000 E"
b1111000 F"
0B"
17"
03"
1C"
1D"
b111 1
b111 ?
b111 2"
b111 K
0F
b111 J
b111 P
b111 Q
1X
0Z
1Y
0[
1U
b11011 $
b11011 +
b11011 7
b11011 N
b11011 (
