entrega/simulation/generated/logica_5bit.v
// Copyright (C) 2021  Intel Corporation. All rights reserved.
// Your use of Intel Corporation's design tools, logic functions 
// and other software and tools, and any partner logic 
// functions, and any output files from any of the foregoing 
// (including device programming or simulation files), and any 
// associated documentation or information are expressly subject 
// to the terms and conditions of the Intel Program License 
// Subscription Agreement, the Intel Quartus Prime License Agreement,
// the Intel FPGA IP License Agreement, or other applicable license
// agreement, including, without limitation, that your use is for
// the sole purpose of programming logic devices manufactured by
// Intel and sold by Intel or its authorized distributors.  Please
// refer to the applicable agreement for further details, at
// https://fpgasoftware.intel.com/eula.


module logica_5bit(
	A_SM,
	B_SM,
	AND6,
	XOR6
);


input wire	[4:0] A_SM;
input wire	[4:0] B_SM;
output wire	[5:0] AND6;
output wire	[5:0] XOR6;

wire	[5:0] AND_ALTERA_SYNTHESIZED6;
wire	[5:0] XOR_ALTERA_SYNTHESIZED6;






assign	AND_ALTERA_SYNTHESIZED6[0] = A_SM[0] & B_SM[0];

assign	AND_ALTERA_SYNTHESIZED6[1] = A_SM[1] & B_SM[1];

assign	AND_ALTERA_SYNTHESIZED6[2] = A_SM[2] & B_SM[2];

assign	AND_ALTERA_SYNTHESIZED6[3] = A_SM[3] & B_SM[3];

assign	AND_ALTERA_SYNTHESIZED6[5] = A_SM[4] & B_SM[4];

assign	XOR_ALTERA_SYNTHESIZED6[0] = A_SM[0] ^ B_SM[0];

assign	XOR_ALTERA_SYNTHESIZED6[1] = A_SM[1] ^ B_SM[1];

assign	XOR_ALTERA_SYNTHESIZED6[2] = A_SM[2] ^ B_SM[2];

assign	XOR_ALTERA_SYNTHESIZED6[3] = A_SM[3] ^ B_SM[3];

assign	XOR_ALTERA_SYNTHESIZED6[5] = A_SM[4] ^ B_SM[4];

assign	AND6 = AND_ALTERA_SYNTHESIZED6;
assign	XOR6 = XOR_ALTERA_SYNTHESIZED6;
assign	AND_ALTERA_SYNTHESIZED6[4] = 0;
assign	XOR_ALTERA_SYNTHESIZED6[4] = 0;

endmodule

entrega/simulation/tb_logica_5bit.sv
module tb_logica_5bit;
logic [4:0] A_SM, B_SM;
wire [5:0] AND6, XOR6;
logic [4:0] ref_and, ref_xor;
logic [5:0] expected_and, expected_xor;
integer ai, bi, tested;
logica_5bit dut(.A_SM(A_SM), .B_SM(B_SM), .AND6(AND6), .XOR6(XOR6));
initial begin
    $dumpfile("waveforms/logica_5bit.vcd");
    $dumpvars(0, tb_logica_5bit);
    tested = 0;
    for (ai = 0; ai < 32; ai = ai + 1) begin
        for (bi = 0; bi < 32; bi = bi + 1) begin
            A_SM = ai[4:0];
            B_SM = bi[4:0];
            #1;
            ref_and = A_SM & B_SM;
            ref_xor = A_SM ^ B_SM;
            expected_and = {ref_and[4], 1'b0, ref_and[3:0]};
            expected_xor = {ref_xor[4], 1'b0, ref_xor[3:0]};
            if (AND6 !== expected_and || XOR6 !== expected_xor)
                $fatal(1, "A=%b B=%b AND6=%b expected=%b XOR6=%b expected=%b", A_SM, B_SM, AND6, expected_and, XOR6, expected_xor);
            tested = tested + 1;
        end
    end
    $display("PASS logica_5bit: %0d pares", tested);
    $finish;
end
endmodule

entrega/simulation/waveforms/logica_5bit.vcd
$date
	Wed Sep 30 02:06:34 2026
$end
$version
	Icarus Verilog
$end
$timescale
	1s
$end
$scope module tb_logica_5bit $end
$var wire 6 ! XOR6 [5:0] $end
$var wire 6 " AND6 [5:0] $end
$var reg 5 # A_SM [4:0] $end
$var reg 5 $ B_SM [4:0] $end
$var reg 6 % expected_and [5:0] $end
$var reg 6 & expected_xor [5:0] $end
$var reg 5 ' ref_and [4:0] $end
$var reg 5 ( ref_xor [4:0] $end
$var integer 32 ) ai [31:0] $end
$var integer 32 * bi [31:0] $end
$var integer 32 + tested [31:0] $end
$scope module dut $end
$var wire 6 , AND6 [5:0] $end
$var wire 5 - A_SM [4:0] $end
$var wire 5 . B_SM [4:0] $end
$var wire 6 / XOR6 [5:0] $end
$var wire 6 0 XOR_ALTERA_SYNTHESIZED6 [5:0] $end
$var wire 6 1 AND_ALTERA_SYNTHESIZED6 [5:0] $end
$upscope $end
$upscope $end
$enddefinitions $end
$comment Show the parameter values. $end
$dumpall
$end
#0
$dumpvars
b0 1
b0 0
b0 /
b0 .
b0 -
b0 ,
b0 +
b0 *
b0 )
bx (
bx '
bx &
bx %
b0 $
b0 #
b0 "
b0 !
$end
#1
b1 !
b1 /
b1 0
b1 $
b1 .
b1 *
b1 +
b0 &
b0 %
b0 (
b0 '
#2
b10 !
b10 /
b10 0
b10 $
b10 .
b10 *
b10 +
b1 &
b1 (
#3
b11 !
b11 /
b11 0
b11 $
b11 .
b11 *
b11 +
b10 &
b10 (
#4
b100 !
b100 /
b100 0
b100 $
b100 .
b100 *
b100 +
b11 &
b11 (
#5
b101 !
b101 /
b101 0
b101 $
b101 .
b101 *
b101 +
b100 &
b100 (
#6
b110 !
b110 /
b110 0
b110 $
b110 .
b110 *
b110 +
b101 &
b101 (
#7
b111 !
b111 /
b111 0
b111 $
b111 .
b111 *
b111 +
b110 &
b110 (
#8
b1000 !
b1000 /
b1000 0
b1000 $
b1000 .
b1000 *
b1000 +
b111 &
b111 (
#9
b1001 !
b1001 /
b1001 0
b1001 $
b1001 .
b1001 *
b1001 +
b1000 &
b1000 (
#10
b1010 !
b1010 /
b1010 0
b1010 $
b1010 .
b1010 *
b1010 +
b1001 &
b1001 (
#11
b1011 !
b1011 /
b1011 0
b1011 $
b1011 .
b1011 *
b1011 +
b1010 &
b1010 (
#12
b1100 !
b1100 /
b1100 0
b1100 $
b1100 .
b1100 *
b1100 +
b1011 &
b1011 (
#13
b1101 !
b1101 /
b1101 0
b1101 $
b1101 .
b1101 *
b1101 +
b1100 &
b1100 (
#14
b1110 !
b1110 /
b1110 0
b1110 $
b1110 .
b1110 *
b1110 +
b1101 &
b1101 (
#15
b1111 !
b1111 /
b1111 0
b1111 $
b1111 .
b1111 *
b1111 +
b1110 &
b1110 (
#16
b100000 !
b100000 /
b100000 0
b10000 $
b10000 .
b10000 *
b10000 +
b1111 &
b1111 (
#17
b100001 !
b100001 /
b100001 0
b10001 $
b10001 .
b10001 *
b10001 +
b100000 &
b10000 (
#18
b100010 !
b100010 /
b100010 0
b10010 $
b10010 .
b10010 *
b10010 +
b100001 &
b10001 (
#19
b100011 !
b100011 /
b100011 0
b10011 $
b10011 .
b10011 *
b10011 +
b100010 &
b10010 (
#20
b100100 !
b100100 /
b100100 0
b10100 $
b10100 .
b10100 *
b10100 +
b100011 &
b10011 (
#21
b100101 !
b100101 /
b100101 0
b10101 $
b10101 .
b10101 *
b10101 +
b100100 &
b10100 (
#22
b100110 !
b100110 /
b100110 0
b10110 $
b10110 .
b10110 *
b10110 +
b100101 &
b10101 (
#23
b100111 !
b100111 /
b100111 0
b10111 $
b10111 .
b10111 *
b10111 +
b100110 &
b10110 (
#24
b101000 !
b101000 /
b101000 0
b11000 $
b11000 .
b11000 *
b11000 +
b100111 &
b10111 (
#25
b101001 !
b101001 /
b101001 0
b11001 $
b11001 .
b11001 *
b11001 +
b101000 &
b11000 (
#26
b101010 !
b101010 /
b101010 0
b11010 $
b11010 .
b11010 *
b11010 +
b101001 &
b11001 (
#27
b101011 !
b101011 /
b101011 0
b11011 $
b11011 .
b11011 *
b11011 +
b101010 &
b11010 (
#28
b101100 !
b101100 /
b101100 0
b11100 $
b11100 .
b11100 *
b11100 +
b101011 &
b11011 (
#29
b101101 !
b101101 /
b101101 0
b11101 $
b11101 .
b11101 *
b11101 +
b101100 &
b11100 (
#30
b101110 !
b101110 /
b101110 0
b11110 $
b11110 .
b11110 *
b11110 +
b101101 &
b11101 (
#31
b101111 !
b101111 /
b101111 0
b11111 $
b11111 .
b11111 *
b11111 +
b101110 &
b11110 (
#32
b1 !
b1 /
b1 0
b0 $
b0 .
b1 #
b1 -
b1 )
b0 *
b100000 +
b101111 &
b11111 (
#33
b1 "
b1 ,
b1 1
b0 !
b0 /
b0 0
b1 $
b1 .
b1 *
b100001 +
b1 &
b1 (
#34
b0 "
b0 ,
b0 1
b11 !
b11 /
b11 0
b10 $
b10 .
b10 *
b100010 +
b0 &
b1 %
b0 (
b1 '
#35
b1 "
b1 ,
b1 1
b10 !
b10 /
b10 0
b11 $
b11 .
b11 *
b100011 +
b11 &
b0 %
b11 (
b0 '
#36
b0 "
b0 ,
b0 1
b101 !
b101 /
b101 0
b100 $
b100 .
b100 *
b100100 +
b10 &
b1 %
b10 (
b1 '
#37
b1 "
b1 ,
b1 1
b100 !
b100 /
b100 0
b101 $
b101 .
b101 *
b100101 +
b101 &
b0 %
b101 (
b0 '
#38
b0 "
b0 ,
b0 1
b111 !
b111 /
b111 0
b110 $
b110 .
b110 *
b100110 +
b100 &
b1 %
b100 (
b1 '
#39
b1 "
b1 ,
b1 1
b110 !
b110 /
b110 0
b111 $
b111 .
b111 *
b100111 +
b111 &
b0 %
b111 (
b0 '
#40
b0 "
b0 ,
b0 1
b1001 !
b1001 /
b1001 0
b1000 $
b1000 .
b1000 *
b101000 +
b110 &
b1 %
b110 (
b1 '
#41
b1 "
b1 ,
b1 1
b1000 !
b1000 /
b1000 0
b1001 $
b1001 .
b1001 *
b101001 +
b1001 &
b0 %
b1001 (
b0 '
#42
b0 "
b0 ,
b0 1
b1011 !
b1011 /
b1011 0
b1010 $
b1010 .
b1010 *
b101010 +
b1000 &
b1 %
b1000 (
b1 '
#43
b1 "
b1 ,
b1 1
b1010 !
b1010 /
b1010 0
b1011 $
b1011 .
b1011 *
b101011 +
b1011 &
b0 %
b1011 (
b0 '
#44
b0 "
b0 ,
b0 1
b1101 !
b1101 /
b1101 0
b1100 $
b1100 .
b1100 *
b101100 +
b1010 &
b1 %
b1010 (
b1 '
#45
b1 "
b1 ,
b1 1
b1100 !
b1100 /
b1100 0
b1101 $
b1101 .
b1101 *
b101101 +
b1101 &
b0 %
b1101 (
b0 '
#46
b0 "
b0 ,
b0 1
b1111 !
b1111 /
b1111 0
b1110 $
b1110 .
b1110 *
b101110 +
b1100 &
b1 %
b1100 (
b1 '
#47
b1 "
b1 ,
b1 1
b1110 !
b1110 /
b1110 0
b1111 $
b1111 .
b1111 *
b101111 +
b1111 &
b0 %
b1111 (
b0 '
#48
b0 "
b0 ,
b0 1
b100001 !
b100001 /
b100001 0
b10000 $
b10000 .
b10000 *
b110000 +
b1110 &
b1 %
b1110 (
b1 '
#49
b1 "
b1 ,
b1 1
b100000 !
b100000 /
b100000 0
b10001 $
b10001 .
b10001 *
b110001 +
b100001 &
b0 %
b10001 (
b0 '
#50
b0 "
b0 ,
b0 1
b100011 !
b100011 /
b100011 0
b10010 $
b10010 .
b10010 *
b110010 +
b100000 &
b1 %
b10000 (
b1 '
#51
b1 "
b1 ,
b1 1
b100010 !
b100010 /
b100010 0
b10011 $
b10011 .
b10011 *
b110011 +
b100011 &
b0 %
b10011 (
b0 '
#52
b0 "
b0 ,
b0 1
b100101 !
b100101 /
b100101 0
b10100 $
b10100 .
b10100 *
b110100 +
b100010 &
b1 %
b10010 (
b1 '
#53
b1 "
b1 ,
b1 1
b100100 !
b100100 /
b100100 0
b10101 $
b10101 .
b10101 *
b110101 +
b100101 &
b0 %
b10101 (
b0 '
#54
b0 "
b0 ,
b0 1
b100111 !
b100111 /
b100111 0
b10110 $
b10110 .
b10110 *
b110110 +
b100100 &
b1 %
b10100 (
b1 '
#55
b1 "
b1 ,
b1 1
b100110 !
b100110 /
b100110 0
b10111 $
b10111 .
b10111 *
b110111 +
b100111 &
b0 %
b10111 (
b0 '
#56
b0 "
b0 ,
b0 1
b101001 !
b101001 /
b101001 0
b11000 $
b11000 .
b11000 *
b111000 +
b100110 &
b1 %
b10110 (
b1 '
#57
b1 "
b1 ,
b1 1
b101000 !
b101000 /
b101000 0
b11001 $
b11001 .
b11001 *
b111001 +
b101001 &
b0 %
b11001 (
b0 '
#58
b0 "
b0 ,
b0 1
b101011 !
b101011 /
b101011 0
b11010 $
b11010 .
b11010 *
b111010 +
b101000 &
b1 %
b11000 (
b1 '
#59
b1 "
b1 ,
b1 1
b101010 !
b101010 /
b101010 0
b11011 $
b11011 .
b11011 *
b111011 +
b101011 &
b0 %
b11011 (
b0 '
#60
b0 "
b0 ,
b0 1
b101101 !
b101101 /
b101101 0
b11100 $
b11100 .
b11100 *
b111100 +
b101010 &
b1 %
b11010 (
b1 '
#61
b1 "
b1 ,
b1 1
b101100 !
b101100 /
b101100 0
b11101 $
b11101 .
b11101 *
b111101 +
b101101 &
b0 %
b11101 (
b0 '
#62
b0 "
b0 ,
b0 1
b101111 !
b101111 /
b101111 0
b11110 $
b11110 .
b11110 *
b111110 +
b101100 &
b1 %
b11100 (
b1 '
#63
b1 "
b1 ,
b1 1
b101110 !
b101110 /
b101110 0
b11111 $
b11111 .
b11111 *
b111111 +
b101111 &
b0 %
b11111 (
b0 '
#64
b10 !
b10 /
b10 0
b0 "
b0 ,
b0 1
b0 $
b0 .
b10 #
b10 -
b10 )
b0 *
b1000000 +
b101110 &
b1 %
b11110 (
b1 '
#65
b11 !
b11 /
b11 0
b1 $
b1 .
b1 *
b1000001 +
b10 &
b0 %
b10 (
b0 '
#66
b10 "
b10 ,
b10 1
b0 !
b0 /
b0 0
b10 $
b10 .
b10 *
b1000010 +
b11 &
b11 (
#67
b1 !
b1 /
b1 0
b11 $
b11 .
b11 *
b1000011 +
b0 &
b10 %
b0 (
b10 '
#68
b0 "
b0 ,
b0 1
b110 !
b110 /
b110 0
b100 $
b100 .
b100 *
b1000100 +
b1 &
b1 (
#69
b111 !
b111 /
b111 0
b101 $
b101 .
b101 *
b1000101 +
b110 &
b0 %
b110 (
b0 '
#70
b10 "
b10 ,
b10 1
b100 !
b100 /
b100 0
b110 $
b110 .
b110 *
b1000110 +
b111 &
b111 (
#71
b101 !
b101 /
b101 0
b111 $
b111 .
b111 *
b1000111 +
b100 &
b10 %
b100 (
b10 '
#72
b0 "
b0 ,
b0 1
b1010 !
b1010 /
b1010 0
b1000 $
b1000 .
b1000 *
b1001000 +
b101 &
b101 (
#73
b1011 !
b1011 /
b1011 0
b1001 $
b1001 .
b1001 *
b1001001 +
b1010 &
b0 %
b1010 (
b0 '
#74
b10 "
b10 ,
b10 1
b1000 !
b1000 /
b1000 0
b1010 $
b1010 .
b1010 *
b1001010 +
b1011 &
b1011 (
#75
b1001 !
b1001 /
b1001 0
b1011 $
b1011 .
b1011 *
b1001011 +
b1000 &
b10 %
b1000 (
b10 '
#76
b0 "
b0 ,
b0 1
b1110 !
b1110 /
b1110 0
b1100 $
b1100 .
b1100 *
b1001100 +
b1001 &
b1001 (
#77
b1111 !
b1111 /
b1111 0
b1101 $
b1101 .
b1101 *
b1001101 +
b1110 &
b0 %
b1110 (
b0 '
#78
b10 "
b10 ,
b10 1
b1100 !
b1100 /
b1100 0
b1110 $
b1110 .
b1110 *
b1001110 +
b1111 &
b1111 (
#79
b1101 !
b1101 /
b1101 0
b1111 $
b1111 .
b1111 *
b1001111 +
b1100 &
b10 %
b1100 (
b10 '
#80
b0 "
b0 ,
b0 1
b100010 !
b100010 /
b100010 0
b10000 $
b10000 .
b10000 *
b1010000 +
b1101 &
b1101 (
#81
b100011 !
b100011 /
b100011 0
b10001 $
b10001 .
b10001 *
b1010001 +
b100010 &
b0 %
b10010 (
b0 '
#82
b10 "
b10 ,
b10 1
b100000 !
b100000 /
b100000 0
b10010 $
b10010 .
b10010 *
b1010010 +
b100011 &
b10011 (
#83
b100001 !
b100001 /
b100001 0
b10011 $
b10011 .
b10011 *
b1010011 +
b100000 &
b10 %
b10000 (
b10 '
#84
b0 "
b0 ,
b0 1
b100110 !
b100110 /
b100110 0
b10100 $
b10100 .
b10100 *
b1010100 +
b100001 &
b10001 (
#85
b100111 !
b100111 /
b100111 0
b10101 $
b10101 .
b10101 *
b1010101 +
b100110 &
b0 %
b10110 (
b0 '
#86
b10 "
b10 ,
b10 1
b100100 !
b100100 /
b100100 0
b10110 $
b10110 .
b10110 *
b1010110 +
b100111 &
b10111 (
#87
b100101 !
b100101 /
b100101 0
b10111 $
b10111 .
b10111 *
b1010111 +
b100100 &
b10 %
b10100 (
b10 '
#88
b0 "
b0 ,
b0 1
b101010 !
b101010 /
b101010 0
b11000 $
b11000 .
b11000 *
b1011000 +
b100101 &
b10101 (
#89
b101011 !
b101011 /
b101011 0
b11001 $
b11001 .
b11001 *
b1011001 +
b101010 &
b0 %
b11010 (
b0 '
#90
b10 "
b10 ,
b10 1
b101000 !
b101000 /
b101000 0
b11010 $
b11010 .
b11010 *
b1011010 +
b101011 &
b11011 (
#91
b101001 !
b101001 /
b101001 0
b11011 $
b11011 .
b11011 *
b1011011 +
b101000 &
b10 %
b11000 (
b10 '
#92
b0 "
b0 ,
b0 1
b101110 !
b101110 /
b101110 0
b11100 $
b11100 .
b11100 *
b1011100 +
b101001 &
b11001 (
#93
b101111 !
b101111 /
b101111 0
b11101 $
b11101 .
b11101 *
b1011101 +
b101110 &
b0 %
b11110 (
b0 '
#94
b10 "
b10 ,
b10 1
b101100 !
b101100 /
b101100 0
b11110 $
b11110 .
b11110 *
b1011110 +
b101111 &
b11111 (
#95
b101101 !
b101101 /
b101101 0
b11111 $
b11111 .
b11111 *
b1011111 +
b101100 &
b10 %
b11100 (
b10 '
#96
b0 "
b0 ,
b0 1
b11 !
b11 /
b11 0
b0 $
b0 .
b11 #
b11 -
b11 )
b0 *
b1100000 +
b101101 &
b11101 (
#97
b1 "
b1 ,
b1 1
b10 !
b10 /
b10 0
b1 $
b1 .
b1 *
b1100001 +
b11 &
b0 %
b11 (
b0 '
#98
b10 "
b10 ,
b10 1
b1 !
b1 /
b1 0
b10 $
b10 .
b10 *
b1100010 +
b10 &
b1 %
b10 (
b1 '
#99
b11 "
b11 ,
b11 1
b0 !
b0 /
b0 0
b11 $
b11 .
b11 *
b1100011 +
b1 &
b10 %
b1 (
b10 '
#100
b0 "
b0 ,
b0 1
b111 !
b111 /
b111 0
b100 $
b100 .
b100 *
b1100100 +
b0 &
b11 %
b0 (
b11 '
#101
b1 "
b1 ,
b1 1
b110 !
b110 /
b110 0
b101 $
b101 .
b101 *
b1100101 +
b111 &
b0 %
b111 (
b0 '
#102
b10 "
b10 ,
b10 1
b101 !
b101 /
b101 0
b110 $
b110 .
b110 *
b1100110 +
b110 &
b1 %
b110 (
b1 '
#103
b11 "
b11 ,
b11 1
b100 !
b100 /
b100 0
b111 $
b111 .
b111 *
b1100111 +
b101 &
b10 %
b101 (
b10 '
#104
b0 "
b0 ,
b0 1
b1011 !
b1011 /
b1011 0
b1000 $
b1000 .
b1000 *
b1101000 +
b100 &
b11 %
b100 (
b11 '
#105
b1 "
b1 ,
b1 1
b1010 !
b1010 /
b1010 0
b1001 $
b1001 .
b1001 *
b1101001 +
b1011 &
b0 %
b1011 (
b0 '
#106
b10 "
b10 ,
b10 1
b1001 !
b1001 /
b1001 0
b1010 $
b1010 .
b1010 *
b1101010 +
b1010 &
b1 %
b1010 (
b1 '
#107
b11 "
b11 ,
b11 1
b1000 !
b1000 /
b1000 0
b1011 $
b1011 .
b1011 *
b1101011 +
b1001 &
b10 %
b1001 (
b10 '
#108
b0 "
b0 ,
b0 1
b1111 !
b1111 /
b1111 0
b1100 $
b1100 .
b1100 *
b1101100 +
b1000 &
b11 %
b1000 (
b11 '
#109
b1 "
b1 ,
b1 1
b1110 !
b1110 /
b1110 0
b1101 $
b1101 .
b1101 *
b1101101 +
b1111 &
b0 %
b1111 (
b0 '
#110
b10 "
b10 ,
b10 1
b1101 !
b1101 /
b1101 0
b1110 $
b1110 .
b1110 *
b1101110 +
b1110 &
b1 %
b1110 (
b1 '
#111
b11 "
b11 ,
b11 1
b1100 !
b1100 /
b1100 0
b1111 $
b1111 .
b1111 *
b1101111 +
b1101 &
b10 %
b1101 (
b10 '
#112
b0 "
b0 ,
b0 1
b100011 !
b100011 /
b100011 0
b10000 $
b10000 .
b10000 *
b1110000 +
b1100 &
b11 %
b1100 (
b11 '
#113
b1 "
b1 ,
b1 1
b100010 !
b100010 /
b100010 0
b10001 $
b10001 .
b10001 *
b1110001 +
b100011 &
b0 %
b10011 (
b0 '
#114
b10 "
b10 ,
b10 1
b100001 !
b100001 /
b100001 0
b10010 $
b10010 .
b10010 *
b1110010 +
b100010 &
b1 %
b10010 (
b1 '
#115
b11 "
b11 ,
b11 1
b100000 !
b100000 /
b100000 0
b10011 $
b10011 .
b10011 *
b1110011 +
b100001 &
b10 %
b10001 (
b10 '
#116
b0 "
b0 ,
b0 1
b100111 !
b100111 /
b100111 0
b10100 $
b10100 .
b10100 *
b1110100 +
b100000 &
b11 %
b10000 (
b11 '
#117
b1 "
b1 ,
b1 1
b100110 !
b100110 /
b100110 0
b10101 $
b10101 .
b10101 *
b1110101 +
b100111 &
b0 %
b10111 (
b0 '
#118
b10 "
b10 ,
b10 1
b100101 !
b100101 /
b100101 0
b10110 $
b10110 .
b10110 *
b1110110 +
b100110 &
b1 %
b10110 (
b1 '
#119
b11 "
b11 ,
b11 1
b100100 !
b100100 /
b100100 0
b10111 $
b10111 .
b10111 *
b1110111 +
b100101 &
b10 %
b10101 (
b10 '
#120
b0 "
b0 ,
b0 1
b101011 !
b101011 /
b101011 0
b11000 $
b11000 .
b11000 *
b1111000 +
b100100 &
b11 %
b10100 (
b11 '
#121
b1 "
b1 ,
b1 1
b101010 !
b101010 /
b101010 0
b11001 $
b11001 .
b11001 *
b1111001 +
b101011 &
b0 %
b11011 (
b0 '
#122
b10 "
b10 ,
b10 1
b101001 !
b101001 /
b101001 0
b11010 $
b11010 .
b11010 *
b1111010 +
b101010 &
b1 %
b11010 (
b1 '
#123
b11 "
b11 ,
b11 1
b101000 !
b101000 /
b101000 0
b11011 $
b11011 .
b11011 *
b1111011 +
b101001 &
b10 %
b11001 (
b10 '
#124
b0 "
b0 ,
b0 1
b101111 !
b101111 /
b101111 0
b11100 $
b11100 .
b11100 *
b1111100 +
b101000 &
b11 %
b11000 (
b11 '
#125
b1 "
b1 ,
b1 1
b101110 !
b101110 /
b101110 0
b11101 $
b11101 .
b11101 *
b1111101 +
b101111 &
b0 %
b11111 (
b0 '
#126
b10 "
b10 ,
b10 1
b101101 !
b101101 /
b101101 0
b11110 $
b11110 .
b11110 *
b1111110 +
b101110 &
b1 %
b11110 (
b1 '
#127
b11 "
b11 ,
b11 1
b101100 !
b101100 /
b101100 0
b11111 $
b11111 .
b11111 *
b1111111 +
b101101 &
b10 %
b11101 (
b10 '
#128
b100 !
b100 /
b100 0
b0 "
b0 ,
b0 1
b0 $
b0 .
b100 #
b100 -
b100 )
b0 *
b10000000 +
b101100 &
b11 %
b11100 (
b11 '
#129
b101 !
b101 /
b101 0
b1 $
b1 .
b1 *
b10000001 +
b100 &
b0 %
b100 (
b0 '
#130
b110 !
b110 /
b110 0
b10 $
b10 .
b10 *
b10000010 +
b101 &
b101 (
#131
b111 !
b111 /
b111 0
b11 $
b11 .
b11 *
b10000011 +
b110 &
b110 (
#132
b100 "
b100 ,
b100 1
b0 !
b0 /
b0 0
b100 $
b100 .
b100 *
b10000100 +
b111 &
b111 (
#133
b1 !
b1 /
b1 0
b101 $
b101 .
b101 *
b10000101 +
b0 &
b100 %
b0 (
b100 '
#134
b10 !
b10 /
b10 0
b110 $
b110 .
b110 *
b10000110 +
b1 &
b1 (
#135
b11 !
b11 /
b11 0
b111 $
b111 .
b111 *
b10000111 +
b10 &
b10 (
#136
b0 "
b0 ,
b0 1
b1100 !
b1100 /
b1100 0
b1000 $
b1000 .
b1000 *
b10001000 +
b11 &
b11 (
#137
b1101 !
b1101 /
b1101 0
b1001 $
b1001 .
b1001 *
b10001001 +
b1100 &
b0 %
b1100 (
b0 '
#138
b1110 !
b1110 /
b1110 0
b1010 $
b1010 .
b1010 *
b10001010 +
b1101 &
b1101 (
#139
b1111 !
b1111 /
b1111 0
b1011 $
b1011 .
b1011 *
b10001011 +
b1110 &
b1110 (
#140
b100 "
b100 ,
b100 1
b1000 !
b1000 /
b1000 0
b1100 $
b1100 .
b1100 *
b10001100 +
b1111 &
b1111 (
#141
b1001 !
b1001 /
b1001 0
b1101 $
b1101 .
b1101 *
b10001101 +
b1000 &
b100 %
b1000 (
b100 '
#142
b1010 !
b1010 /
b1010 0
b1110 $
b1110 .
b1110 *
b10001110 +
b1001 &
b1001 (
#143
b1011 !
b1011 /
b1011 0
b1111 $
b1111 .
b1111 *
b10001111 +
b1010 &
b1010 (
#144
b0 "
b0 ,
b0 1
b100100 !
b100100 /
b100100 0
b10000 $
b10000 .
b10000 *
b10010000 +
b1011 &
b1011 (
#145
b100101 !
b100101 /
b100101 0
b10001 $
b10001 .
b10001 *
b10010001 +
b100100 &
b0 %
b10100 (
b0 '
#146
b100110 !
b100110 /
b100110 0
b10010 $
b10010 .
b10010 *
b10010010 +
b100101 &
b10101 (
#147
b100111 !
b100111 /
b100111 0
b10011 $
b10011 .
b10011 *
b10010011 +
b100110 &
b10110 (
#148
b100 "
b100 ,
b100 1
b100000 !
b100000 /
b100000 0
b10100 $
b10100 .
b10100 *
b10010100 +
b100111 &
b10111 (
#149
b100001 !
b100001 /
b100001 0
b10101 $
b10101 .
b10101 *
b10010101 +
b100000 &
b100 %
b10000 (
b100 '
#150
b100010 !
b100010 /
b100010 0
b10110 $
b10110 .
b10110 *
b10010110 +
b100001 &
b10001 (
#151
b100011 !
b100011 /
b100011 0
b10111 $
b10111 .
b10111 *
b10010111 +
b100010 &
b10010 (
#152
b0 "
b0 ,
b0 1
b101100 !
b101100 /
b101100 0
b11000 $
b11000 .
b11000 *
b10011000 +
b100011 &
b10011 (
#153
b101101 !
b101101 /
b101101 0
b11001 $
b11001 .
b11001 *
b10011001 +
b101100 &
b0 %
b11100 (
b0 '
#154
b101110 !
b101110 /
b101110 0
b11010 $
b11010 .
b11010 *
b10011010 +
b101101 &
b11101 (
#155
b101111 !
b101111 /
b101111 0
b11011 $
b11011 .
b11011 *
b10011011 +
b101110 &
b11110 (
#156
b100 "
b100 ,
b100 1
b101000 !
b101000 /
b101000 0
b11100 $
b11100 .
b11100 *
b10011100 +
b101111 &
b11111 (
#157
b101001 !
b101001 /
b101001 0
b11101 $
b11101 .
b11101 *
b10011101 +
b101000 &
b100 %
b11000 (
b100 '
#158
b101010 !
b101010 /
b101010 0
b11110 $
b11110 .
b11110 *
b10011110 +
b101001 &
b11001 (
#159
b101011 !
b101011 /
b101011 0
b11111 $
b11111 .
b11111 *
b10011111 +
b101010 &
b11010 (
#160
b0 "
b0 ,
b0 1
b101 !
b101 /
b101 0
b0 $
b0 .
b101 #
b101 -
b101 )
b0 *
b10100000 +
b101011 &
b11011 (
#161
b1 "
b1 ,
b1 1
b100 !
b100 /
b100 0
b1 $
b1 .
b1 *
b10100001 +
b101 &
b0 %
b101 (
b0 '
#162
b0 "
b0 ,
b0 1
b111 !
b111 /
b111 0
b10 $
b10 .
b10 *
b10100010 +
b100 &
b1 %
b100 (
b1 '
#163
b1 "
b1 ,
b1 1
b110 !
b110 /
b110 0
b11 $
b11 .
b11 *
b10100011 +
b111 &
b0 %
b111 (
b0 '
#164
b100 "
b100 ,
b100 1
b1 !
b1 /
b1 0
b100 $
b100 .
b100 *
b10100100 +
b110 &
b1 %
b110 (
b1 '
#165
b101 "
b101 ,
b101 1
b0 !
b0 /
b0 0
b101 $
b101 .
b101 *
b10100101 +
b1 &
b100 %
b1 (
b100 '
#166
b100 "
b100 ,
b100 1
b11 !
b11 /
b11 0
b110 $
b110 .
b110 *
b10100110 +
b0 &
b101 %
b0 (
b101 '
#167
b101 "
b101 ,
b101 1
b10 !
b10 /
b10 0
b111 $
b111 .
b111 *
b10100111 +
b11 &
b100 %
b11 (
b100 '
#168
b0 "
b0 ,
b0 1
b1101 !
b1101 /
b1101 0
b1000 $
b1000 .
b1000 *
b10101000 +
b10 &
b101 %
b10 (
b101 '
#169
b1 "
b1 ,
b1 1
b1100 !
b1100 /
b1100 0
b1001 $
b1001 .
b1001 *
b10101001 +
b1101 &
b0 %
b1101 (
b0 '
#170
b0 "
b0 ,
b0 1
b1111 !
b1111 /
b1111 0
b1010 $
b1010 .
b1010 *
b10101010 +
b1100 &
b1 %
b1100 (
b1 '
#171
b1 "
b1 ,
b1 1
b1110 !
b1110 /
b1110 0
b1011 $
b1011 .
b1011 *
b10101011 +
b1111 &
b0 %
b1111 (
b0 '
#172
b100 "
b100 ,
b100 1
b1001 !
b1001 /
b1001 0
b1100 $
b1100 .
b1100 *
b10101100 +
b1110 &
b1 %
b1110 (
b1 '
#173
b101 "
b101 ,
b101 1
b1000 !
b1000 /
b1000 0
b1101 $
b1101 .
b1101 *
b10101101 +
b1001 &
b100 %
b1001 (
b100 '
#174
b100 "
b100 ,
b100 1
b1011 !
b1011 /
b1011 0
b1110 $
b1110 .
b1110 *
b10101110 +
b1000 &
b101 %
b1000 (
b101 '
#175
b101 "
b101 ,
b101 1
b1010 !
b1010 /
b1010 0
b1111 $
b1111 .
b1111 *
b10101111 +
b1011 &
b100 %
b1011 (
b100 '
#176
b0 "
b0 ,
b0 1
b100101 !
b100101 /
b100101 0
b10000 $
b10000 .
b10000 *
b10110000 +
b1010 &
b101 %
b1010 (
b101 '
#177
b1 "
b1 ,
b1 1
b100100 !
b100100 /
b100100 0
b10001 $
b10001 .
b10001 *
b10110001 +
b100101 &
b0 %
b10101 (
b0 '
#178
b0 "
b0 ,
b0 1
b100111 !
b100111 /
b100111 0
b10010 $
b10010 .
b10010 *
b10110010 +
b100100 &
b1 %
b10100 (
b1 '
