entrega/simulation/generated/mux_resultado_8x6.v
// Copyright (C) 2021  Intel Corporation. All rights reserved.
// Your use of Intel Corporation's design tools, logic functions 
// and other software and tools, and any partner logic 
// functions, and any output files from any of the foregoing 
// (including device programming or simulation files), and any 
// associated documentation or information are expressly subject 
// to the terms and conditions of the Intel Program License 
// Subscription Agreement, the Intel Quartus Prime License Agreement,
// the Intel FPGA IP License Agreement, or other applicable license
// agreement, including, without limitation, that your use is for
// the sole purpose of programming logic devices manufactured by
// Intel and sold by Intel or its authorized distributors.  Please
// refer to the applicable agreement for further details, at
// https://fpgasoftware.intel.com/eula.


module mux_resultado_8x6(
	C0,
	C1,
	C2,
	C3,
	C4,
	C5,
	C6,
	C7,
	D,
	F
);


input wire	[5:0] C0;
input wire	[5:0] C1;
input wire	[5:0] C2;
input wire	[5:0] C3;
input wire	[5:0] C4;
input wire	[5:0] C5;
input wire	[5:0] C6;
input wire	[5:0] C7;
input wire	[7:0] D;
output wire	[5:0] F;

wire	[5:0] F_ALTERA_SYNTHESIZED;
wire	P_0_0;
wire	P_0_1;
wire	P_0_2;
wire	P_0_3;
wire	P_0_4;
wire	P_0_5;
wire	P_1_0;
wire	P_1_1;
wire	P_1_2;
wire	P_1_3;
wire	P_1_4;
wire	P_1_5;
wire	P_2_0;
wire	P_2_1;
wire	P_2_2;
wire	P_2_3;
wire	P_2_4;
wire	P_2_5;
wire	P_3_0;
wire	P_3_1;
wire	P_3_2;
wire	P_3_3;
wire	P_3_4;
wire	P_3_5;
wire	P_4_0;
wire	P_4_1;
wire	P_4_2;
wire	P_4_3;
wire	P_4_4;
wire	P_4_5;
wire	P_5_0;
wire	P_5_1;
wire	P_5_2;
wire	P_5_3;
wire	P_5_4;
wire	P_5_5;
wire	P_6_0;
wire	P_6_1;
wire	P_6_2;
wire	P_6_3;
wire	P_6_4;
wire	P_6_5;
wire	P_7_0;
wire	P_7_1;
wire	P_7_2;
wire	P_7_3;
wire	P_7_4;
wire	P_7_5;




assign	P_0_0 = C0[0] & D[0];

assign	P_0_1 = C0[1] & D[0];

assign	P_0_2 = C0[2] & D[0];

assign	P_0_3 = C0[3] & D[0];

assign	P_0_4 = C0[4] & D[0];

assign	P_0_5 = C0[5] & D[0];

assign	P_1_0 = C1[0] & D[1];

assign	P_1_1 = C1[1] & D[1];

assign	P_1_2 = C1[2] & D[1];

assign	P_1_3 = C1[3] & D[1];

assign	P_1_4 = C1[4] & D[1];

assign	P_1_5 = C1[5] & D[1];

assign	P_2_0 = C2[0] & D[2];

assign	P_2_1 = C2[1] & D[2];

assign	P_2_2 = C2[2] & D[2];

assign	P_2_3 = C2[3] & D[2];

assign	P_2_4 = C2[4] & D[2];

assign	P_2_5 = C2[5] & D[2];

assign	P_3_0 = C3[0] & D[3];

assign	P_3_1 = C3[1] & D[3];

assign	P_3_2 = C3[2] & D[3];

assign	P_3_3 = C3[3] & D[3];

assign	P_3_4 = C3[4] & D[3];

assign	P_3_5 = C3[5] & D[3];

assign	P_4_0 = C4[0] & D[4];

assign	P_4_1 = C4[1] & D[4];

assign	P_4_2 = C4[2] & D[4];

assign	P_4_3 = C4[3] & D[4];

assign	P_4_4 = C4[4] & D[4];

assign	P_4_5 = C4[5] & D[4];

assign	P_5_0 = C5[0] & D[5];

assign	P_5_1 = C5[1] & D[5];

assign	P_5_2 = C5[2] & D[5];

assign	P_5_3 = C5[3] & D[5];

assign	P_5_4 = C5[4] & D[5];

assign	P_5_5 = C5[5] & D[5];

assign	P_6_0 = C6[0] & D[6];

assign	P_6_1 = C6[1] & D[6];

assign	P_6_2 = C6[2] & D[6];

assign	P_6_3 = C6[3] & D[6];

assign	P_6_4 = C6[4] & D[6];

assign	P_6_5 = C6[5] & D[6];

assign	P_7_0 = C7[0] & D[7];

assign	P_7_1 = C7[1] & D[7];

assign	P_7_2 = C7[2] & D[7];

assign	P_7_3 = C7[3] & D[7];

assign	P_7_4 = C7[4] & D[7];

assign	P_7_5 = C7[5] & D[7];

assign	F_ALTERA_SYNTHESIZED[0] = P_0_0 | P_2_0 | P_1_0 | P_3_0 | P_5_0 | P_4_0 | P_6_0 | P_7_0;

assign	F_ALTERA_SYNTHESIZED[1] = P_0_1 | P_2_1 | P_1_1 | P_3_1 | P_5_1 | P_4_1 | P_6_1 | P_7_1;

assign	F_ALTERA_SYNTHESIZED[2] = P_0_2 | P_2_2 | P_1_2 | P_3_2 | P_5_2 | P_4_2 | P_6_2 | P_7_2;

assign	F_ALTERA_SYNTHESIZED[3] = P_0_3 | P_2_3 | P_1_3 | P_3_3 | P_5_3 | P_4_3 | P_6_3 | P_7_3;

assign	F_ALTERA_SYNTHESIZED[4] = P_0_4 | P_2_4 | P_1_4 | P_3_4 | P_5_4 | P_4_4 | P_6_4 | P_7_4;

assign	F_ALTERA_SYNTHESIZED[5] = P_0_5 | P_2_5 | P_1_5 | P_3_5 | P_5_5 | P_4_5 | P_6_5 | P_7_5;

assign	F = F_ALTERA_SYNTHESIZED;

endmodule

entrega/simulation/tb_mux_resultado_8x6.sv
module tb_mux_resultado_8x6;
logic [5:0] C0, C1, C2, C3, C4, C5, C6, C7;
logic [7:0] D;
wire [5:0] F;
integer si, value, tested;
mux_resultado_8x6 dut(.C0(C0), .C1(C1), .C2(C2), .C3(C3), .C4(C4), .C5(C5), .C6(C6), .C7(C7), .D(D), .F(F));
initial begin
    $dumpfile("waveforms/mux_resultado_8x6.vcd");
    $dumpvars(0, tb_mux_resultado_8x6);
    tested = 0;
    C0 = 0; C1 = 0; C2 = 0; C3 = 0; C4 = 0; C5 = 0; C6 = 0; C7 = 0;
    for (si = 0; si < 8; si = si + 1) begin
        D = 8'b1 << si;
        for (value = 0; value < 64; value = value + 1) begin
            C0 = 0; C1 = 0; C2 = 0; C3 = 0; C4 = 0; C5 = 0; C6 = 0; C7 = 0;
            case (si)
                0: C0 = value[5:0];
                1: C1 = value[5:0];
                2: C2 = value[5:0];
                3: C3 = value[5:0];
                4: C4 = value[5:0];
                5: C5 = value[5:0];
                6: C6 = value[5:0];
                7: C7 = value[5:0];
            endcase
            #1;
            if (F !== value[5:0])
                $fatal(1, "D=%b candidato C%0d=%02h F=%02h expected=%02h", D, si, value[5:0], F, value[5:0]);
            tested = tested + 1;
        end
    end
    $display("PASS mux_resultado_8x6: %0d estímulos um-hot", tested);
    $finish;
end
endmodule

entrega/simulation/waveforms/mux_resultado_8x6.vcd
$date
	Wed Sep 30 02:06:34 2026
$end
$version
	Icarus Verilog
$end
$timescale
	1s
$end
$scope module tb_mux_resultado_8x6 $end
$var wire 6 ! F [5:0] $end
$var reg 6 " C0 [5:0] $end
$var reg 6 # C1 [5:0] $end
$var reg 6 $ C2 [5:0] $end
$var reg 6 % C3 [5:0] $end
$var reg 6 & C4 [5:0] $end
$var reg 6 ' C5 [5:0] $end
$var reg 6 ( C6 [5:0] $end
$var reg 6 ) C7 [5:0] $end
$var reg 8 * D [7:0] $end
$var integer 32 + si [31:0] $end
$var integer 32 , tested [31:0] $end
$var integer 32 - value [31:0] $end
$scope module dut $end
$var wire 6 . C0 [5:0] $end
$var wire 6 / C1 [5:0] $end
$var wire 6 0 C2 [5:0] $end
$var wire 6 1 C3 [5:0] $end
$var wire 6 2 C4 [5:0] $end
$var wire 6 3 C5 [5:0] $end
$var wire 6 4 C6 [5:0] $end
$var wire 6 5 C7 [5:0] $end
$var wire 8 6 D [7:0] $end
$var wire 6 7 F [5:0] $end
$var wire 1 8 P_0_0 $end
$var wire 1 9 P_0_1 $end
$var wire 1 : P_0_2 $end
$var wire 1 ; P_0_3 $end
$var wire 1 < P_0_4 $end
$var wire 1 = P_0_5 $end
$var wire 1 > P_1_0 $end
$var wire 1 ? P_1_1 $end
$var wire 1 @ P_1_2 $end
$var wire 1 A P_1_3 $end
$var wire 1 B P_1_4 $end
$var wire 1 C P_1_5 $end
$var wire 1 D P_2_0 $end
$var wire 1 E P_2_1 $end
$var wire 1 F P_2_2 $end
$var wire 1 G P_2_3 $end
$var wire 1 H P_2_4 $end
$var wire 1 I P_2_5 $end
$var wire 1 J P_3_0 $end
$var wire 1 K P_3_1 $end
$var wire 1 L P_3_2 $end
$var wire 1 M P_3_3 $end
$var wire 1 N P_3_4 $end
$var wire 1 O P_3_5 $end
$var wire 1 P P_4_0 $end
$var wire 1 Q P_4_1 $end
$var wire 1 R P_4_2 $end
$var wire 1 S P_4_3 $end
$var wire 1 T P_4_4 $end
$var wire 1 U P_4_5 $end
$var wire 1 V P_5_0 $end
$var wire 1 W P_5_1 $end
$var wire 1 X P_5_2 $end
$var wire 1 Y P_5_3 $end
$var wire 1 Z P_5_4 $end
$var wire 1 [ P_5_5 $end
$var wire 1 \ P_6_0 $end
$var wire 1 ] P_6_1 $end
$var wire 1 ^ P_6_2 $end
$var wire 1 _ P_6_3 $end
$var wire 1 ` P_6_4 $end
$var wire 1 a P_6_5 $end
$var wire 1 b P_7_0 $end
$var wire 1 c P_7_1 $end
$var wire 1 d P_7_2 $end
$var wire 1 e P_7_3 $end
$var wire 1 f P_7_4 $end
$var wire 1 g P_7_5 $end
$var wire 6 h F_ALTERA_SYNTHESIZED [5:0] $end
$upscope $end
$upscope $end
$enddefinitions $end
$comment Show the parameter values. $end
$dumpall
$end
#0
$dumpvars
b0 h
0g
0f
0e
0d
0c
0b
0a
0`
0_
0^
0]
0\
0[
0Z
0Y
0X
0W
0V
0U
0T
0S
0R
0Q
0P
0O
0N
0M
0L
0K
0J
0I
0H
0G
0F
0E
0D
0C
0B
0A
0@
0?
0>
0=
0<
0;
0:
09
08
b0 7
b1 6
b0 5
b0 4
b0 3
b0 2
b0 1
b0 0
b0 /
b0 .
b0 -
b0 ,
b0 +
b1 *
b0 )
b0 (
b0 '
b0 &
b0 %
b0 $
b0 #
b0 "
b0 !
$end
#1
b1 !
b1 7
b1 h
18
b1 "
b1 .
b1 -
b1 ,
#2
b10 !
b10 7
b10 h
19
08
b10 "
b10 .
b10 -
b10 ,
#3
b11 !
b11 7
b11 h
18
b11 "
b11 .
b11 -
b11 ,
#4
b100 !
b100 7
b100 h
1:
08
09
b100 "
b100 .
b100 -
b100 ,
#5
b101 !
b101 7
b101 h
18
b101 "
b101 .
b101 -
b101 ,
#6
b110 !
b110 7
b110 h
19
08
b110 "
b110 .
b110 -
b110 ,
#7
b111 !
b111 7
b111 h
18
b111 "
b111 .
b111 -
b111 ,
#8
b1000 !
b1000 7
b1000 h
1;
08
09
0:
b1000 "
b1000 .
b1000 -
b1000 ,
#9
b1001 !
b1001 7
b1001 h
18
b1001 "
b1001 .
b1001 -
b1001 ,
#10
b1010 !
b1010 7
b1010 h
19
08
b1010 "
b1010 .
b1010 -
b1010 ,
#11
b1011 !
b1011 7
b1011 h
18
b1011 "
b1011 .
b1011 -
b1011 ,
#12
b1100 !
b1100 7
b1100 h
1:
08
09
b1100 "
b1100 .
b1100 -
b1100 ,
#13
b1101 !
b1101 7
b1101 h
18
b1101 "
b1101 .
b1101 -
b1101 ,
#14
b1110 !
b1110 7
b1110 h
19
08
b1110 "
b1110 .
b1110 -
b1110 ,
#15
b1111 !
b1111 7
b1111 h
18
b1111 "
b1111 .
b1111 -
b1111 ,
#16
b10000 !
b10000 7
b10000 h
1<
08
09
0:
0;
b10000 "
b10000 .
b10000 -
b10000 ,
#17
b10001 !
b10001 7
b10001 h
18
b10001 "
b10001 .
b10001 -
b10001 ,
#18
b10010 !
b10010 7
b10010 h
19
08
b10010 "
b10010 .
b10010 -
b10010 ,
#19
b10011 !
b10011 7
b10011 h
18
b10011 "
b10011 .
b10011 -
b10011 ,
#20
b10100 !
b10100 7
b10100 h
1:
08
09
b10100 "
b10100 .
b10100 -
b10100 ,
#21
b10101 !
b10101 7
b10101 h
18
b10101 "
b10101 .
b10101 -
b10101 ,
#22
b10110 !
b10110 7
b10110 h
19
08
b10110 "
b10110 .
b10110 -
b10110 ,
#23
b10111 !
b10111 7
b10111 h
18
b10111 "
b10111 .
b10111 -
b10111 ,
#24
b11000 !
b11000 7
b11000 h
1;
08
09
0:
b11000 "
b11000 .
b11000 -
b11000 ,
#25
b11001 !
b11001 7
b11001 h
18
b11001 "
b11001 .
b11001 -
b11001 ,
#26
b11010 !
b11010 7
b11010 h
19
08
b11010 "
b11010 .
b11010 -
b11010 ,
#27
b11011 !
b11011 7
b11011 h
18
b11011 "
b11011 .
b11011 -
b11011 ,
#28
b11100 !
b11100 7
b11100 h
1:
08
09
b11100 "
b11100 .
b11100 -
b11100 ,
#29
b11101 !
b11101 7
b11101 h
18
b11101 "
b11101 .
b11101 -
b11101 ,
#30
b11110 !
b11110 7
b11110 h
19
08
b11110 "
b11110 .
b11110 -
b11110 ,
#31
b11111 !
b11111 7
b11111 h
18
b11111 "
b11111 .
b11111 -
b11111 ,
#32
b100000 !
b100000 7
b100000 h
1=
08
09
0:
0;
0<
b100000 "
b100000 .
b100000 -
b100000 ,
#33
b100001 !
b100001 7
b100001 h
18
b100001 "
b100001 .
b100001 -
b100001 ,
#34
b100010 !
b100010 7
b100010 h
19
08
b100010 "
b100010 .
b100010 -
b100010 ,
#35
b100011 !
b100011 7
b100011 h
18
b100011 "
b100011 .
b100011 -
b100011 ,
#36
b100100 !
b100100 7
b100100 h
1:
08
09
b100100 "
b100100 .
b100100 -
b100100 ,
#37
b100101 !
b100101 7
b100101 h
18
b100101 "
b100101 .
b100101 -
b100101 ,
#38
b100110 !
b100110 7
b100110 h
19
08
b100110 "
b100110 .
b100110 -
b100110 ,
#39
b100111 !
b100111 7
b100111 h
18
b100111 "
b100111 .
b100111 -
b100111 ,
#40
b101000 !
b101000 7
b101000 h
1;
08
09
0:
b101000 "
b101000 .
b101000 -
b101000 ,
#41
b101001 !
b101001 7
b101001 h
18
b101001 "
b101001 .
b101001 -
b101001 ,
#42
b101010 !
b101010 7
b101010 h
19
08
b101010 "
b101010 .
b101010 -
b101010 ,
#43
b101011 !
b101011 7
b101011 h
18
b101011 "
b101011 .
b101011 -
b101011 ,
#44
b101100 !
b101100 7
b101100 h
1:
08
09
b101100 "
b101100 .
b101100 -
b101100 ,
#45
b101101 !
b101101 7
b101101 h
18
b101101 "
b101101 .
b101101 -
b101101 ,
#46
b101110 !
b101110 7
b101110 h
19
08
b101110 "
b101110 .
b101110 -
b101110 ,
#47
b101111 !
b101111 7
b101111 h
18
b101111 "
b101111 .
b101111 -
b101111 ,
#48
b110000 !
b110000 7
b110000 h
1<
08
09
0:
0;
b110000 "
b110000 .
b110000 -
b110000 ,
#49
b110001 !
b110001 7
b110001 h
18
b110001 "
b110001 .
b110001 -
b110001 ,
#50
b110010 !
b110010 7
b110010 h
19
08
b110010 "
b110010 .
b110010 -
b110010 ,
#51
b110011 !
b110011 7
b110011 h
18
b110011 "
b110011 .
b110011 -
b110011 ,
#52
b110100 !
b110100 7
b110100 h
1:
08
09
b110100 "
b110100 .
b110100 -
b110100 ,
#53
b110101 !
b110101 7
b110101 h
18
b110101 "
b110101 .
b110101 -
b110101 ,
#54
b110110 !
b110110 7
b110110 h
19
08
b110110 "
b110110 .
b110110 -
b110110 ,
#55
b110111 !
b110111 7
b110111 h
18
b110111 "
b110111 .
b110111 -
b110111 ,
#56
b111000 !
b111000 7
b111000 h
1;
08
09
0:
b111000 "
b111000 .
b111000 -
b111000 ,
#57
b111001 !
b111001 7
b111001 h
18
b111001 "
b111001 .
b111001 -
b111001 ,
#58
b111010 !
b111010 7
b111010 h
19
08
b111010 "
b111010 .
b111010 -
b111010 ,
#59
b111011 !
b111011 7
b111011 h
18
b111011 "
b111011 .
b111011 -
b111011 ,
#60
b111100 !
b111100 7
b111100 h
1:
08
09
b111100 "
b111100 .
b111100 -
b111100 ,
#61
b111101 !
b111101 7
b111101 h
18
b111101 "
b111101 .
b111101 -
b111101 ,
#62
b111110 !
b111110 7
b111110 h
19
08
b111110 "
b111110 .
b111110 -
b111110 ,
#63
b111111 !
b111111 7
b111111 h
18
b111111 "
b111111 .
b111111 -
b111111 ,
#64
b0 !
b0 7
b0 h
08
09
0:
0;
0<
0=
b0 "
b0 .
b10 *
b10 6
b1 +
b0 -
b1000000 ,
#65
b1 !
b1 7
b1 h
1>
b1 #
b1 /
b1 -
b1000001 ,
#66
b10 !
b10 7
b10 h
1?
0>
b10 #
b10 /
b10 -
b1000010 ,
#67
b11 !
b11 7
b11 h
1>
b11 #
b11 /
b11 -
b1000011 ,
#68
b100 !
b100 7
b100 h
1@
0>
0?
b100 #
b100 /
b100 -
b1000100 ,
#69
b101 !
b101 7
b101 h
1>
b101 #
b101 /
b101 -
b1000101 ,
#70
b110 !
b110 7
b110 h
1?
0>
b110 #
b110 /
b110 -
b1000110 ,
#71
b111 !
b111 7
b111 h
1>
b111 #
b111 /
b111 -
b1000111 ,
#72
b1000 !
b1000 7
b1000 h
1A
0>
0?
0@
b1000 #
b1000 /
b1000 -
b1001000 ,
#73
b1001 !
b1001 7
b1001 h
1>
b1001 #
b1001 /
b1001 -
b1001001 ,
#74
b1010 !
b1010 7
b1010 h
1?
0>
b1010 #
b1010 /
b1010 -
b1001010 ,
#75
b1011 !
b1011 7
b1011 h
1>
b1011 #
b1011 /
b1011 -
b1001011 ,
#76
b1100 !
b1100 7
b1100 h
1@
0>
0?
b1100 #
b1100 /
b1100 -
b1001100 ,
#77
b1101 !
b1101 7
b1101 h
1>
b1101 #
b1101 /
b1101 -
b1001101 ,
#78
b1110 !
b1110 7
b1110 h
1?
0>
b1110 #
b1110 /
b1110 -
b1001110 ,
#79
b1111 !
b1111 7
b1111 h
1>
b1111 #
b1111 /
b1111 -
b1001111 ,
#80
b10000 !
b10000 7
b10000 h
1B
0>
0?
0@
0A
b10000 #
b10000 /
b10000 -
b1010000 ,
#81
b10001 !
b10001 7
b10001 h
1>
b10001 #
b10001 /
b10001 -
b1010001 ,
#82
b10010 !
b10010 7
b10010 h
1?
0>
b10010 #
b10010 /
b10010 -
b1010010 ,
#83
b10011 !
b10011 7
b10011 h
1>
b10011 #
b10011 /
b10011 -
b1010011 ,
#84
b10100 !
b10100 7
b10100 h
1@
0>
0?
b10100 #
b10100 /
b10100 -
b1010100 ,
#85
b10101 !
b10101 7
b10101 h
1>
b10101 #
b10101 /
b10101 -
b1010101 ,
#86
b10110 !
b10110 7
b10110 h
1?
0>
b10110 #
b10110 /
b10110 -
b1010110 ,
#87
b10111 !
b10111 7
b10111 h
1>
b10111 #
b10111 /
b10111 -
b1010111 ,
#88
b11000 !
b11000 7
b11000 h
1A
0>
0?
0@
b11000 #
b11000 /
b11000 -
b1011000 ,
#89
b11001 !
b11001 7
b11001 h
1>
b11001 #
b11001 /
b11001 -
b1011001 ,
#90
b11010 !
b11010 7
b11010 h
1?
0>
b11010 #
b11010 /
b11010 -
b1011010 ,
#91
b11011 !
b11011 7
b11011 h
1>
b11011 #
b11011 /
b11011 -
b1011011 ,
#92
b11100 !
b11100 7
b11100 h
1@
0>
0?
b11100 #
b11100 /
b11100 -
b1011100 ,
#93
b11101 !
b11101 7
b11101 h
1>
b11101 #
b11101 /
b11101 -
b1011101 ,
#94
b11110 !
b11110 7
b11110 h
1?
0>
b11110 #
b11110 /
b11110 -
b1011110 ,
#95
b11111 !
b11111 7
b11111 h
1>
b11111 #
b11111 /
b11111 -
b1011111 ,
#96
b100000 !
b100000 7
b100000 h
1C
0>
0?
0@
0A
0B
b100000 #
b100000 /
b100000 -
b1100000 ,
#97
b100001 !
b100001 7
b100001 h
1>
b100001 #
b100001 /
b100001 -
b1100001 ,
#98
b100010 !
b100010 7
b100010 h
1?
0>
b100010 #
b100010 /
b100010 -
b1100010 ,
#99
b100011 !
b100011 7
b100011 h
1>
b100011 #
b100011 /
b100011 -
b1100011 ,
#100
b100100 !
b100100 7
b100100 h
1@
0>
0?
b100100 #
b100100 /
b100100 -
b1100100 ,
#101
b100101 !
b100101 7
b100101 h
1>
b100101 #
b100101 /
b100101 -
b1100101 ,
#102
b100110 !
b100110 7
b100110 h
1?
0>
b100110 #
b100110 /
b100110 -
b1100110 ,
#103
b100111 !
b100111 7
b100111 h
1>
b100111 #
b100111 /
b100111 -
b1100111 ,
#104
b101000 !
b101000 7
b101000 h
1A
0>
0?
0@
b101000 #
b101000 /
b101000 -
b1101000 ,
#105
b101001 !
b101001 7
b101001 h
1>
b101001 #
b101001 /
b101001 -
b1101001 ,
#106
b101010 !
b101010 7
b101010 h
1?
0>
b101010 #
b101010 /
b101010 -
b1101010 ,
#107
b101011 !
b101011 7
b101011 h
1>
b101011 #
b101011 /
b101011 -
b1101011 ,
#108
b101100 !
b101100 7
b101100 h
1@
0>
0?
b101100 #
b101100 /
b101100 -
b1101100 ,
#109
b101101 !
b101101 7
b101101 h
1>
b101101 #
b101101 /
b101101 -
b1101101 ,
#110
b101110 !
b101110 7
b101110 h
1?
0>
b101110 #
b101110 /
b101110 -
b1101110 ,
#111
b101111 !
b101111 7
b101111 h
1>
b101111 #
b101111 /
b101111 -
b1101111 ,
#112
b110000 !
b110000 7
b110000 h
1B
0>
0?
0@
0A
b110000 #
b110000 /
b110000 -
b1110000 ,
#113
b110001 !
b110001 7
b110001 h
1>
b110001 #
b110001 /
b110001 -
b1110001 ,
#114
b110010 !
b110010 7
b110010 h
1?
0>
b110010 #
b110010 /
b110010 -
b1110010 ,
#115
b110011 !
b110011 7
b110011 h
1>
b110011 #
b110011 /
b110011 -
b1110011 ,
#116
b110100 !
b110100 7
b110100 h
1@
0>
0?
b110100 #
b110100 /
b110100 -
b1110100 ,
#117
b110101 !
b110101 7
b110101 h
1>
b110101 #
b110101 /
b110101 -
b1110101 ,
#118
b110110 !
b110110 7
b110110 h
1?
0>
b110110 #
b110110 /
b110110 -
b1110110 ,
#119
b110111 !
b110111 7
b110111 h
1>
b110111 #
b110111 /
b110111 -
b1110111 ,
#120
b111000 !
b111000 7
b111000 h
1A
0>
0?
0@
b111000 #
b111000 /
b111000 -
b1111000 ,
#121
b111001 !
b111001 7
b111001 h
1>
b111001 #
b111001 /
b111001 -
b1111001 ,
#122
b111010 !
b111010 7
b111010 h
1?
0>
b111010 #
b111010 /
b111010 -
b1111010 ,
#123
b111011 !
b111011 7
b111011 h
1>
b111011 #
b111011 /
b111011 -
b1111011 ,
#124
b111100 !
b111100 7
b111100 h
1@
0>
0?
b111100 #
b111100 /
b111100 -
b1111100 ,
#125
b111101 !
b111101 7
b111101 h
1>
b111101 #
b111101 /
b111101 -
b1111101 ,
#126
b111110 !
b111110 7
b111110 h
1?
0>
b111110 #
b111110 /
b111110 -
b1111110 ,
#127
b111111 !
b111111 7
b111111 h
1>
b111111 #
b111111 /
b111111 -
b1111111 ,
#128
b0 !
b0 7
b0 h
0>
0?
0@
0A
0B
0C
b0 #
b0 /
b100 *
b100 6
b10 +
b0 -
b10000000 ,
#129
b1 !
b1 7
b1 h
1D
b1 $
b1 0
b1 -
b10000001 ,
#130
b10 !
b10 7
b10 h
1E
0D
b10 $
b10 0
b10 -
b10000010 ,
#131
b11 !
b11 7
b11 h
1D
b11 $
b11 0
b11 -
b10000011 ,
#132
b100 !
b100 7
b100 h
1F
0D
0E
b100 $
b100 0
b100 -
b10000100 ,
#133
b101 !
b101 7
b101 h
1D
b101 $
b101 0
b101 -
b10000101 ,
#134
b110 !
b110 7
b110 h
1E
0D
b110 $
b110 0
b110 -
b10000110 ,
#135
b111 !
b111 7
b111 h
1D
b111 $
b111 0
b111 -
b10000111 ,
#136
b1000 !
b1000 7
b1000 h
1G
0D
0E
0F
b1000 $
b1000 0
b1000 -
b10001000 ,
#137
b1001 !
b1001 7
b1001 h
1D
b1001 $
b1001 0
b1001 -
b10001001 ,
#138
b1010 !
b1010 7
b1010 h
1E
0D
b1010 $
b1010 0
b1010 -
b10001010 ,
#139
b1011 !
b1011 7
b1011 h
1D
b1011 $
b1011 0
b1011 -
b10001011 ,
#140
b1100 !
b1100 7
b1100 h
1F
0D
0E
b1100 $
b1100 0
b1100 -
b10001100 ,
#141
b1101 !
b1101 7
b1101 h
1D
b1101 $
b1101 0
b1101 -
b10001101 ,
#142
b1110 !
b1110 7
b1110 h
1E
0D
b1110 $
b1110 0
b1110 -
b10001110 ,
#143
b1111 !
b1111 7
b1111 h
1D
b1111 $
b1111 0
b1111 -
b10001111 ,
#144
b10000 !
b10000 7
b10000 h
1H
0D
0E
0F
0G
b10000 $
b10000 0
b10000 -
b10010000 ,
#145
b10001 !
b10001 7
b10001 h
1D
b10001 $
b10001 0
b10001 -
b10010001 ,
#146
b10010 !
b10010 7
b10010 h
1E
0D
b10010 $
b10010 0
b10010 -
b10010010 ,
#147
b10011 !
b10011 7
b10011 h
1D
b10011 $
b10011 0
b10011 -
b10010011 ,
#148
b10100 !
b10100 7
b10100 h
1F
0D
0E
b10100 $
b10100 0
b10100 -
b10010100 ,
#149
b10101 !
b10101 7
b10101 h
1D
b10101 $
b10101 0
b10101 -
b10010101 ,
#150
b10110 !
b10110 7
b10110 h
1E
0D
b10110 $
b10110 0
b10110 -
b10010110 ,
#151
b10111 !
b10111 7
b10111 h
1D
b10111 $
b10111 0
b10111 -
b10010111 ,
#152
b11000 !
b11000 7
b11000 h
1G
0D
0E
0F
b11000 $
b11000 0
b11000 -
b10011000 ,
#153
b11001 !
b11001 7
b11001 h
1D
b11001 $
b11001 0
b11001 -
b10011001 ,
#154
b11010 !
b11010 7
b11010 h
1E
0D
b11010 $
b11010 0
b11010 -
b10011010 ,
#155
b11011 !
b11011 7
b11011 h
1D
b11011 $
b11011 0
b11011 -
b10011011 ,
#156
b11100 !
b11100 7
b11100 h
1F
0D
0E
b11100 $
b11100 0
b11100 -
b10011100 ,
#157
b11101 !
b11101 7
b11101 h
1D
b11101 $
b11101 0
b11101 -
b10011101 ,
#158
b11110 !
b11110 7
b11110 h
1E
0D
b11110 $
b11110 0
b11110 -
b10011110 ,
#159
b11111 !
b11111 7
b11111 h
1D
b11111 $
b11111 0
b11111 -
b10011111 ,
#160
b100000 !
b100000 7
b100000 h
1I
0D
0E
0F
0G
0H
b100000 $
b100000 0
b100000 -
b10100000 ,
#161
b100001 !
b100001 7
b100001 h
1D
b100001 $
b100001 0
b100001 -
b10100001 ,
#162
b100010 !
b100010 7
b100010 h
1E
0D
b100010 $
b100010 0
b100010 -
b10100010 ,
#163
b100011 !
b100011 7
b100011 h
1D
b100011 $
b100011 0
b100011 -
b10100011 ,
#164
b100100 !
b100100 7
b100100 h
1F
0D
0E
b100100 $
b100100 0
b100100 -
b10100100 ,
#165
b100101 !
b100101 7
b100101 h
1D
b100101 $
b100101 0
b100101 -
b10100101 ,
#166
b100110 !
b100110 7
b100110 h
1E
0D
b100110 $
b100110 0
b100110 -
b10100110 ,
#167
b100111 !
b100111 7
b100111 h
1D
b100111 $
b100111 0
b100111 -
b10100111 ,
#168
b101000 !
b101000 7
b101000 h
1G
0D
0E
0F
b101000 $
b101000 0
b101000 -
b10101000 ,
#169
b101001 !
b101001 7
b101001 h
1D
b101001 $
b101001 0
b101001 -
b10101001 ,
#170
b101010 !
b101010 7
b101010 h
1E
0D
b101010 $
b101010 0
b101010 -
b10101010 ,
#171
b101011 !
b101011 7
b101011 h
1D
b101011 $
b101011 0
b101011 -
b10101011 ,
#172
b101100 !
b101100 7
b101100 h
1F
0D
0E
b101100 $
b101100 0
b101100 -
b10101100 ,
#173
b101101 !
b101101 7
b101101 h
1D
b101101 $
b101101 0
b101101 -
b10101101 ,
#174
b101110 !
b101110 7
b101110 h
1E
0D
b101110 $
b101110 0
b101110 -
b10101110 ,
#175
b101111 !
b101111 7
b101111 h
1D
b101111 $
b101111 0
b101111 -
b10101111 ,
#176
b110000 !
b110000 7
b110000 h
1H
0D
0E
0F
0G
b110000 $
b110000 0
b110000 -
b10110000 ,
#177
b110001 !
b110001 7
b110001 h
1D
b110001 $
b110001 0
b110001 -
b10110001 ,
#178
b110010 !
b110010 7
b110010 h
1E
0D
b110010 $
b110010 0
b110010 -
b10110010 ,
#179
b110011 !
b110011 7
b110011 h
1D
b110011 $
b110011 0
b110011 -
b10110011 ,
#180
b110100 !
b110100 7
b110100 h
1F
0D
0E
b110100 $
b110100 0
b110100 -
b10110100 ,
#181
b110101 !
b110101 7
b110101 h
1D
b110101 $
b110101 0
b110101 -
b10110101 ,
#182
b110110 !
b110110 7
b110110 h
1E
0D
b110110 $
b110110 0
b110110 -
b10110110 ,
#183
b110111 !
b110111 7
b110111 h
1D
b110111 $
b110111 0
b110111 -
b10110111 ,
#184
b111000 !
b111000 7
b111000 h
1G
0D
0E
0F
b111000 $
b111000 0
b111000 -
b10111000 ,
#185
b111001 !
b111001 7
b111001 h
1D
b111001 $
b111001 0
b111001 -
b10111001 ,
#186
b111010 !
b111010 7
b111010 h
1E
0D
b111010 $
b111010 0
b111010 -
b10111010 ,
#187
b111011 !
b111011 7
b111011 h
1D
b111011 $
b111011 0
b111011 -
b10111011 ,
#188
b111100 !
b111100 7
b111100 h
1F
0D
0E
b111100 $
b111100 0
b111100 -
b10111100 ,
#189
b111101 !
b111101 7
b111101 h
1D
b111101 $
b111101 0
b111101 -
b10111101 ,
#190
b111110 !
b111110 7
b111110 h
1E
0D
b111110 $
b111110 0
b111110 -
b10111110 ,
#191
b111111 !
b111111 7
b111111 h
1D
b111111 $
b111111 0
b111111 -
b10111111 ,
#192
b0 !
b0 7
b0 h
0D
0E
0F
0G
0H
0I
b0 $
b0 0
b1000 *
b1000 6
b11 +
b0 -
b11000000 ,
#193
b1 !
b1 7
b1 h
1J
b1 %
b1 1
b1 -
b11000001 ,
#194
b10 !
b10 7
b10 h
1K
0J
b10 %
b10 1
b10 -
b11000010 ,
#195
b11 !
b11 7
b11 h
1J
b11 %
b11 1
b11 -
b11000011 ,
