entrega/simulation/generated/somador_1bit.v
// Copyright (C) 2021  Intel Corporation. All rights reserved.
// Your use of Intel Corporation's design tools, logic functions 
// and other software and tools, and any partner logic 
// functions, and any output files from any of the foregoing 
// (including device programming or simulation files), and any 
// associated documentation or information are expressly subject 
// to the terms and conditions of the Intel Program License 
// Subscription Agreement, the Intel Quartus Prime License Agreement,
// the Intel FPGA IP License Agreement, or other applicable license
// agreement, including, without limitation, that your use is for
// the sole purpose of programming logic devices manufactured by
// Intel and sold by Intel or its authorized distributors.  Please
// refer to the applicable agreement for further details, at
// https://fpgasoftware.intel.com/eula.


module somador_1bit(
	A,
	B,
	Cin,
	S,
	Cout
);


input wire	A;
input wire	B;
input wire	Cin;
output wire	S;
output wire	Cout;

wire	fa_G;
wire	fa_H;
wire	fa_P;




assign	fa_G = A & B;

assign	fa_H = fa_P & Cin;

assign	Cout = fa_H | fa_G;

assign	fa_P = A ^ B;

assign	S = fa_P ^ Cin;


endmodule

entrega/simulation/tb_somador_1bit.sv
module tb_somador_1bit;
reg A;
reg B;
reg Cin;
wire S;
wire Cout;
integer a;
integer b;
integer c;
integer total;
integer checks;
somador_1bit dut(.A(A),.B(B),.Cin(Cin),.S(S),.Cout(Cout));
initial begin
  $dumpfile("waveforms/somador_1bit.vcd");
  $dumpvars(0,tb_somador_1bit);
  checks=0;
  for(a=0;a<2;a=a+1) begin
    for(b=0;b<2;b=b+1) begin
      for(c=0;c<2;c=c+1) begin
        A=a; B=b; Cin=c; #1;
        total=a+b+c;
        if ({Cout,S} !== total[1:0]) $fatal(1,"somador_1bit A=%0d B=%0d Cin=%0d obtido=%b esperado=%b",a,b,c,{Cout,S},total[1:0]);
        checks=checks+1;
      end
    end
  end
  if(checks!=8) $fatal(1,"cobertura incompleta: %0d",checks);
  $display("tb_somador_1bit PASS checks=%0d",checks);
  $finish;
end
endmodule

entrega/simulation/waveforms/somador_1bit.vcd
$date
	Wed Sep 30 02:06:33 2026
$end
$version
	Icarus Verilog
$end
$timescale
	1s
$end
$scope module tb_somador_1bit $end
$var wire 1 ! S $end
$var wire 1 " Cout $end
$var reg 1 # A $end
$var reg 1 $ B $end
$var reg 1 % Cin $end
$var integer 32 & a [31:0] $end
$var integer 32 ' b [31:0] $end
$var integer 32 ( c [31:0] $end
$var integer 32 ) checks [31:0] $end
$var integer 32 * total [31:0] $end
$scope module dut $end
$var wire 1 # A $end
$var wire 1 $ B $end
$var wire 1 % Cin $end
$var wire 1 " Cout $end
$var wire 1 ! S $end
$var wire 1 + fa_G $end
$var wire 1 , fa_H $end
$var wire 1 - fa_P $end
$upscope $end
$upscope $end
$enddefinitions $end
$comment Show the parameter values. $end
$dumpall
$end
#0
$dumpvars
0-
0,
0+
bx *
b0 )
b0 (
b0 '
b0 &
0%
0$
0#
0"
0!
$end
#1
1!
1%
b1 (
b1 )
b0 *
#2
1-
0%
1$
b1 '
b0 (
b10 )
b1 *
#3
1"
1,
0!
1%
b1 (
b11 )
#4
0"
0,
1!
0%
0$
1#
b1 &
b0 '
b0 (
b100 )
b10 *
#5
1"
1,
0!
1%
b1 (
b101 )
b1 *
#6
0,
1+
0-
0%
1$
b1 '
b0 (
b110 )
b10 *
#7
1!
1%
b1 (
b111 )
#8
b10 &
b10 '
b10 (
b1000 )
b11 *
