entrega/simulation/generated/somador_1bit.v
// Copyright (C) 2021  Intel Corporation. All rights reserved.
// Your use of Intel Corporation's design tools, logic functions 
// and other software and tools, and any partner logic 
// functions, and any output files from any of the foregoing 
// (including device programming or simulation files), and any 
// associated documentation or information are expressly subject 
// to the terms and conditions of the Intel Program License 
// Subscription Agreement, the Intel Quartus Prime License Agreement,
// the Intel FPGA IP License Agreement, or other applicable license
// agreement, including, without limitation, that your use is for
// the sole purpose of programming logic devices manufactured by
// Intel and sold by Intel or its authorized distributors.  Please
// refer to the applicable agreement for further details, at
// https://fpgasoftware.intel.com/eula.


module somador_1bit(
	A,
	B,
	Cin,
	S,
	Cout
);


input wire	A;
input wire	B;
input wire	Cin;
output wire	S;
output wire	Cout;

wire	fa_G;
wire	fa_H;
wire	fa_P;




assign	fa_G = A & B;

assign	fa_H = fa_P & Cin;

assign	Cout = fa_H | fa_G;

assign	fa_P = A ^ B;

assign	S = fa_P ^ Cin;


endmodule

entrega/simulation/generated/somador_subtrator_6bit.v
// Copyright (C) 2021  Intel Corporation. All rights reserved.
// Your use of Intel Corporation's design tools, logic functions 
// and other software and tools, and any partner logic 
// functions, and any output files from any of the foregoing 
// (including device programming or simulation files), and any 
// associated documentation or information are expressly subject 
// to the terms and conditions of the Intel Program License 
// Subscription Agreement, the Intel Quartus Prime License Agreement,
// the Intel FPGA IP License Agreement, or other applicable license
// agreement, including, without limitation, that your use is for
// the sole purpose of programming logic devices manufactured by
// Intel and sold by Intel or its authorized distributors.  Please
// refer to the applicable agreement for further details, at
// https://fpgasoftware.intel.com/eula.


module somador_subtrator_6bit(
	SUB,
	A,
	B,
	Cout,
	R
);


input wire	SUB;
input wire	[5:0] A;
input wire	[5:0] B;
output wire	Cout;
output wire	[5:0] R;

wire	[5:0] BX;
wire	[5:1] CARRY;
wire	[5:0] R_ALTERA_SYNTHESIZED;





somador_1bit	b2v_fa_0(
	.A(A[0]),
	.B(BX[0]),
	.Cin(SUB),
	.S(R_ALTERA_SYNTHESIZED[0]),
	.Cout(CARRY[1]));


somador_1bit	b2v_fa_1(
	.A(A[1]),
	.B(BX[1]),
	.Cin(CARRY[1]),
	.S(R_ALTERA_SYNTHESIZED[1]),
	.Cout(CARRY[2]));


somador_1bit	b2v_fa_2(
	.A(A[2]),
	.B(BX[2]),
	.Cin(CARRY[2]),
	.S(R_ALTERA_SYNTHESIZED[2]),
	.Cout(CARRY[3]));


somador_1bit	b2v_fa_3(
	.A(A[3]),
	.B(BX[3]),
	.Cin(CARRY[3]),
	.S(R_ALTERA_SYNTHESIZED[3]),
	.Cout(CARRY[4]));


somador_1bit	b2v_fa_4(
	.A(A[4]),
	.B(BX[4]),
	.Cin(CARRY[4]),
	.S(R_ALTERA_SYNTHESIZED[4]),
	.Cout(CARRY[5]));


somador_1bit	b2v_fa_5(
	.A(A[5]),
	.B(BX[5]),
	.Cin(CARRY[5]),
	.S(R_ALTERA_SYNTHESIZED[5]),
	.Cout(Cout));

assign	BX[0] = B[0] ^ SUB;

assign	BX[1] = B[1] ^ SUB;

assign	BX[2] = B[2] ^ SUB;

assign	BX[3] = B[3] ^ SUB;

assign	BX[4] = B[4] ^ SUB;

assign	BX[5] = B[5] ^ SUB;

assign	R = R_ALTERA_SYNTHESIZED;

endmodule

entrega/simulation/tb_somador_subtrator_6bit.sv
module tb_somador_subtrator_6bit;
reg [5:0] A;
reg [5:0] B;
reg SUB;
wire [5:0] R;
wire Cout;
integer a;
integer b;
integer sub;
integer total;
integer checks;
reg [6:0] expected;
somador_subtrator_6bit dut(.A(A),.B(B),.SUB(SUB),.R(R),.Cout(Cout));
initial begin
  $dumpfile("waveforms/somador_subtrator_6bit.vcd");
  $dumpvars(0,tb_somador_subtrator_6bit);
  checks=0;
  for(a=0;a<64;a=a+1) begin
    for(b=0;b<64;b=b+1) begin
      for(sub=0;sub<2;sub=sub+1) begin
        A=a; B=b; SUB=sub; #1;
        total=a+(b ^ (sub ? 63 : 0))+sub;
        expected=total;
        if({Cout,R} !== expected) $fatal(1,"A=%0d B=%0d SUB=%0d obtido=%b esperado=%b",a,b,sub,{Cout,R},expected);
        checks=checks+1;
      end
    end
  end
  if(checks!=8192) $fatal(1,"cobertura incompleta: %0d",checks);
  $display("tb_somador_subtrator_6bit PASS checks=%0d",checks);
  $finish;
end
endmodule

entrega/simulation/waveforms/somador_subtrator_6bit.vcd
$date
	Wed Sep 30 02:06:33 2026
$end
$version
	Icarus Verilog
$end
$timescale
	1s
$end
$scope module tb_somador_subtrator_6bit $end
$var wire 6 ! R [5:0] $end
$var wire 1 " Cout $end
$var reg 6 # A [5:0] $end
$var reg 6 $ B [5:0] $end
$var reg 1 % SUB $end
$var reg 7 & expected [6:0] $end
$var integer 32 ' a [31:0] $end
$var integer 32 ( b [31:0] $end
$var integer 32 ) checks [31:0] $end
$var integer 32 * sub [31:0] $end
$var integer 32 + total [31:0] $end
$scope module dut $end
$var wire 6 , A [5:0] $end
$var wire 6 - B [5:0] $end
$var wire 6 . R [5:0] $end
$var wire 1 % SUB $end
$var wire 6 / R_ALTERA_SYNTHESIZED [5:0] $end
$var wire 1 " Cout $end
$var wire 5 0 CARRY [5:1] $end
$var wire 6 1 BX [5:0] $end
$scope module b2v_fa_0 $end
$var wire 1 2 A $end
$var wire 1 3 B $end
$var wire 1 % Cin $end
$var wire 1 4 Cout $end
$var wire 1 5 S $end
$var wire 1 6 fa_G $end
$var wire 1 7 fa_H $end
$var wire 1 8 fa_P $end
$upscope $end
$scope module b2v_fa_1 $end
$var wire 1 9 A $end
$var wire 1 : B $end
$var wire 1 ; Cin $end
$var wire 1 < Cout $end
$var wire 1 = S $end
$var wire 1 > fa_G $end
$var wire 1 ? fa_H $end
$var wire 1 @ fa_P $end
$upscope $end
$scope module b2v_fa_2 $end
$var wire 1 A A $end
$var wire 1 B B $end
$var wire 1 C Cin $end
$var wire 1 D Cout $end
$var wire 1 E S $end
$var wire 1 F fa_G $end
$var wire 1 G fa_H $end
$var wire 1 H fa_P $end
$upscope $end
$scope module b2v_fa_3 $end
$var wire 1 I A $end
$var wire 1 J B $end
$var wire 1 K Cin $end
$var wire 1 L Cout $end
$var wire 1 M S $end
$var wire 1 N fa_G $end
$var wire 1 O fa_H $end
$var wire 1 P fa_P $end
$upscope $end
$scope module b2v_fa_4 $end
$var wire 1 Q A $end
$var wire 1 R B $end
$var wire 1 S Cin $end
$var wire 1 T Cout $end
$var wire 1 U S $end
$var wire 1 V fa_G $end
$var wire 1 W fa_H $end
$var wire 1 X fa_P $end
$upscope $end
$scope module b2v_fa_5 $end
$var wire 1 Y A $end
$var wire 1 Z B $end
$var wire 1 [ Cin $end
$var wire 1 " Cout $end
$var wire 1 \ S $end
$var wire 1 ] fa_G $end
$var wire 1 ^ fa_H $end
$var wire 1 _ fa_P $end
$upscope $end
$upscope $end
$upscope $end
$enddefinitions $end
$comment Show the parameter values. $end
$dumpall
$end
#0
$dumpvars
0_
0^
0]
0\
0[
0Z
0Y
0X
0W
0V
0U
0T
0S
0R
0Q
0P
0O
0N
0M
0L
0K
0J
0I
0H
0G
0F
0E
0D
0C
0B
0A
0@
0?
0>
0=
0<
0;
0:
09
08
07
06
05
04
03
02
b0 1
b0 0
b0 /
b0 .
b0 -
b0 ,
bx +
b0 *
b0 )
b0 (
b0 '
bx &
0%
b0 $
b0 #
0"
b0 !
$end
#1
1"
1^
1[
1T
1W
1S
1L
1O
1K
1D
1G
1C
1<
1?
1;
b11111 0
14
0\
0U
0M
0E
0=
17
1_
1X
1P
1H
1@
18
1Z
1R
1J
1B
1:
13
b111111 1
b0 !
b0 .
b0 /
05
1%
b1 *
b1 )
b0 &
b0 +
#2
0[
0S
0K
0C
0"
0T
0L
0D
0<
0\
0^
0U
0W
0M
0O
0E
0G
0?
0_
0X
0P
0H
0@
0;
0Z
0R
0J
0B
0:
b0 0
b1 1
b1 !
b1 .
b1 /
04
07
15
0%
b1 $
b1 -
b1 (
b0 *
b10 )
b1000000 &
b1000000 +
#3
0"
0^
0[
0T
0W
0S
0L
0O
0K
0D
0G
1=
0C
0<
1\
1U
1M
1E
0?
1_
1X
1P
1H
1@
08
0;
1Z
1R
1J
1B
1:
03
b0 0
b111110 1
b111111 !
b111111 .
b111111 /
04
07
15
1%
b1 *
b11 )
b1 &
b1 +
#4
0\
0U
0M
0E
0_
0X
0P
0H
0Z
0R
0J
0B
b10 1
b10 !
b10 .
b10 /
05
0%
b10 $
b10 -
b10 (
b0 *
b100 )
b111111 &
b111111 +
#5
1;
b1 0
14
1\
1U
1M
1E
1=
17
1_
1X
1P
1H
0@
18
1Z
1R
1J
1B
0:
13
b111101 1
b111110 !
b111110 .
b111110 /
05
1%
b1 *
b101 )
b10 &
b10 +
#6
0\
0U
0M
0E
0_
0X
0P
0H
1@
0;
0Z
0R
0J
0B
1:
b0 0
b11 1
b11 !
b11 .
b11 /
04
07
15
0%
b11 $
b11 -
b11 (
b0 *
b110 )
b111110 &
b111110 +
#7
0=
1\
1U
1M
1E
1_
1X
1P
1H
0@
08
0;
1Z
1R
1J
1B
0:
03
b0 0
b111100 1
b111101 !
b111101 .
b111101 /
04
07
15
1%
b1 *
b111 )
b11 &
b11 +
#8
0\
0U
0M
0_
0X
0P
0Z
0R
0J
b100 1
b100 !
b100 .
b100 /
05
0%
b100 $
b100 -
b100 (
b0 *
b1000 )
b111101 &
b111101 +
#9
1C
1<
1?
1;
b11 0
14
1\
1U
1M
1E
0=
17
1_
1X
1P
0H
1@
18
1Z
1R
1J
0B
1:
13
b111011 1
b111100 !
b111100 .
b111100 /
05
1%
b1 *
b1001 )
b100 &
b100 +
#10
0K
0C
0D
0<
0\
0U
0M
1E
0G
0?
0_
0X
0P
1H
0@
0;
0Z
0R
0J
1B
0:
b0 0
b101 1
b101 !
b101 .
b101 /
04
07
15
0%
b101 $
b101 -
b101 (
b0 *
b1010 )
b111100 &
b111100 +
#11
1=
0C
0<
1\
1U
1M
0E
0?
1_
1X
1P
0H
1@
08
0;
1Z
1R
1J
0B
1:
03
b0 0
b111010 1
b111011 !
b111011 .
b111011 /
04
07
15
1%
b1 *
b1011 )
b101 &
b101 +
#12
0\
0U
0M
1E
0_
0X
0P
1H
0Z
0R
0J
1B
b110 1
b110 !
b110 .
b110 /
05
0%
b110 $
b110 -
b110 (
b0 *
b1100 )
b111011 &
b111011 +
#13
1;
b1 0
14
1\
1U
1M
0E
1=
17
1_
1X
1P
0H
0@
18
1Z
1R
1J
0B
0:
13
b111001 1
b111010 !
b111010 .
b111010 /
05
1%
b1 *
b1101 )
b110 &
b110 +
#14
0\
0U
0M
1E
0_
0X
0P
1H
1@
0;
0Z
0R
0J
1B
1:
b0 0
b111 1
b111 !
b111 .
b111 /
04
07
15
0%
b111 $
b111 -
b111 (
b0 *
b1110 )
b111010 &
b111010 +
#15
0=
1\
1U
1M
0E
1_
1X
1P
0H
0@
08
0;
1Z
1R
1J
0B
0:
03
b0 0
b111000 1
b111001 !
b111001 .
b111001 /
04
07
15
1%
b1 *
b1111 )
b111 &
b111 +
#16
0\
0U
0_
0X
0Z
0R
b1000 1
b1000 !
b1000 .
b1000 /
05
0%
b1000 $
b1000 -
b1000 (
b0 *
b10000 )
b111001 &
b111001 +
#17
1K
1D
1G
1C
1<
1?
1;
b111 0
14
1\
1U
1M
0E
0=
17
1_
1X
0P
1H
1@
18
1Z
1R
0J
1B
1:
13
b110111 1
b111000 !
b111000 .
b111000 /
05
1%
b1 *
b10001 )
b1000 &
b1000 +
#18
0S
0K
0C
0L
0D
0<
0\
0U
1M
0O
0E
0G
0?
0_
0X
1P
0H
0@
0;
0Z
0R
1J
0B
0:
b0 0
b1001 1
b1001 !
b1001 .
b1001 /
04
07
15
0%
b1001 $
b1001 -
b1001 (
b0 *
b10010 )
b111000 &
b111000 +
#19
0K
0D
0G
1=
0C
0<
1\
1U
0M
1E
0?
1_
1X
0P
1H
1@
08
0;
1Z
1R
0J
1B
1:
03
b0 0
b110110 1
b110111 !
b110111 .
b110111 /
04
07
15
1%
b1 *
b10011 )
b1001 &
b1001 +
#20
0\
0U
1M
0E
0_
0X
1P
0H
0Z
0R
1J
0B
b1010 1
b1010 !
b1010 .
b1010 /
05
0%
b1010 $
b1010 -
b1010 (
b0 *
b10100 )
b110111 &
b110111 +
#21
1;
b1 0
14
1\
1U
0M
1E
1=
17
1_
1X
0P
1H
0@
18
1Z
1R
0J
1B
0:
13
b110101 1
b110110 !
b110110 .
b110110 /
05
1%
b1 *
b10101 )
b1010 &
b1010 +
#22
0\
0U
1M
0E
0_
0X
1P
0H
1@
0;
0Z
0R
1J
0B
1:
b0 0
b1011 1
b1011 !
b1011 .
b1011 /
04
07
15
0%
b1011 $
b1011 -
b1011 (
b0 *
b10110 )
b110110 &
b110110 +
#23
0=
1\
1U
0M
1E
1_
1X
0P
1H
0@
08
0;
1Z
1R
0J
1B
0:
03
b0 0
b110100 1
b110101 !
b110101 .
b110101 /
04
07
15
1%
b1 *
b10111 )
b1011 &
b1011 +
#24
0\
0U
1M
0_
0X
1P
0Z
0R
1J
b1100 1
b1100 !
b1100 .
b1100 /
05
0%
b1100 $
b1100 -
b1100 (
b0 *
b11000 )
b110101 &
b110101 +
#25
1C
1<
1?
1;
b11 0
14
1\
1U
0M
1E
0=
17
1_
1X
0P
0H
1@
18
1Z
1R
0J
0B
1:
13
b110011 1
b110100 !
b110100 .
b110100 /
05
1%
b1 *
b11001 )
b1100 &
b1100 +
#26
0S
0L
0O
0K
0C
0D
0<
0\
0U
1M
1E
0G
0?
0_
0X
1P
1H
0@
0;
0Z
0R
1J
1B
0:
b0 0
b1101 1
b1101 !
b1101 .
b1101 /
04
07
15
0%
b1101 $
b1101 -
b1101 (
b0 *
b11010 )
b110100 &
b110100 +
#27
1=
0C
0<
1\
1U
0M
0E
0?
1_
1X
0P
0H
1@
08
0;
1Z
1R
0J
0B
1:
03
b0 0
b110010 1
b110011 !
b110011 .
b110011 /
04
07
15
1%
b1 *
b11011 )
b1101 &
b1101 +
#28
0\
0U
1M
1E
0_
0X
1P
1H
0Z
0R
1J
1B
b1110 1
b1110 !
b1110 .
b1110 /
05
0%
b1110 $
b1110 -
b1110 (
b0 *
b11100 )
b110011 &
b110011 +
#29
1;
b1 0
14
1\
1U
0M
0E
1=
17
1_
1X
0P
0H
0@
18
1Z
1R
0J
0B
0:
13
b110001 1
b110010 !
b110010 .
b110010 /
05
1%
b1 *
b11101 )
b1110 &
b1110 +
#30
0\
0U
1M
1E
0_
0X
1P
1H
1@
0;
0Z
0R
1J
1B
1:
b0 0
b1111 1
b1111 !
b1111 .
b1111 /
04
07
15
0%
b1111 $
b1111 -
b1111 (
b0 *
b11110 )
b110010 &
b110010 +
#31
0=
1\
1U
0M
0E
1_
1X
0P
0H
0@
08
0;
1Z
1R
0J
0B
0:
03
b0 0
b110000 1
b110001 !
b110001 .
b110001 /
04
07
15
1%
b1 *
b11111 )
b1111 &
b1111 +
#32
0\
0_
0Z
b10000 1
b10000 !
b10000 .
b10000 /
05
0%
b10000 $
b10000 -
b10000 (
b0 *
b100000 )
b110001 &
b110001 +
#33
1S
1L
1O
1K
1D
1G
1C
1<
1?
1;
b1111 0
14
1\
1U
0M
0E
0=
17
1_
0X
1P
1H
1@
18
1Z
0R
1J
1B
1:
13
b101111 1
b110000 !
b110000 .
b110000 /
05
1%
b1 *
b100001 )
b10000 &
b10000 +
#34
0[
0S
0K
0C
0T
0L
0D
0<
0\
1U
0W
0M
0O
0E
0G
0?
0_
1X
0P
0H
0@
0;
0Z
1R
0J
0B
0:
b0 0
b10001 1
b10001 !
b10001 .
b10001 /
04
07
15
0%
b10001 $
b10001 -
b10001 (
b0 *
b100010 )
b110000 &
b110000 +
#35
0S
0L
0O
0K
0D
0G
1=
0C
0<
1\
0U
1M
1E
0?
1_
0X
1P
1H
1@
08
0;
1Z
0R
1J
1B
1:
03
b0 0
b101110 1
b101111 !
b101111 .
b101111 /
04
07
15
1%
b1 *
b100011 )
b10001 &
b10001 +
#36
0\
1U
0M
0E
0_
1X
0P
0H
0Z
1R
0J
0B
b10010 1
b10010 !
b10010 .
b10010 /
05
0%
b10010 $
b10010 -
b10010 (
b0 *
b100100 )
b101111 &
b101111 +
#37
1;
b1 0
14
1\
0U
1M
1E
1=
17
1_
0X
1P
1H
0@
18
1Z
0R
1J
1B
0:
13
b101101 1
b101110 !
b101110 .
b101110 /
05
1%
b1 *
b100101 )
b10010 &
b10010 +
#38
0\
1U
0M
0E
0_
1X
0P
0H
1@
0;
0Z
1R
0J
0B
1:
b0 0
b10011 1
b10011 !
b10011 .
b10011 /
04
07
15
0%
b10011 $
b10011 -
b10011 (
b0 *
b100110 )
b101110 &
b101110 +
#39
0=
1\
0U
1M
1E
1_
0X
1P
1H
0@
08
0;
1Z
0R
1J
1B
0:
03
b0 0
b101100 1
b101101 !
b101101 .
b101101 /
04
07
15
1%
b1 *
b100111 )
b10011 &
b10011 +
#40
0\
1U
0M
0_
1X
0P
0Z
1R
0J
b10100 1
b10100 !
b10100 .
b10100 /
05
0%
b10100 $
b10100 -
b10100 (
b0 *
b101000 )
b101101 &
b101101 +
#41
1C
1<
1?
1;
b11 0
14
1\
0U
1M
1E
0=
17
1_
0X
1P
0H
1@
18
1Z
0R
1J
0B
1:
13
b101011 1
b101100 !
b101100 .
b101100 /
05
1%
b1 *
b101001 )
b10100 &
b10100 +
#42
0K
0C
0D
0<
0\
1U
0M
1E
0G
0?
0_
1X
0P
1H
0@
0;
0Z
1R
0J
1B
0:
b0 0
b10101 1
b10101 !
b10101 .
b10101 /
04
07
15
0%
b10101 $
b10101 -
b10101 (
b0 *
b101010 )
b101100 &
b101100 +
#43
1=
0C
0<
1\
0U
1M
0E
0?
1_
0X
1P
0H
1@
08
0;
1Z
0R
1J
0B
1:
03
b0 0
b101010 1
b101011 !
b101011 .
b101011 /
04
07
15
1%
b1 *
b101011 )
b10101 &
b10101 +
#44
0\
1U
0M
1E
0_
1X
0P
1H
0Z
1R
0J
1B
b10110 1
b10110 !
b10110 .
b10110 /
05
0%
b10110 $
b10110 -
b10110 (
b0 *
b101100 )
b101011 &
b101011 +
#45
1;
b1 0
14
1\
0U
1M
0E
1=
17
1_
0X
1P
0H
0@
18
1Z
0R
1J
0B
0:
13
b101001 1
b101010 !
b101010 .
b101010 /
05
1%
b1 *
b101101 )
b10110 &
b10110 +
#46
0\
1U
0M
1E
0_
1X
0P
1H
1@
0;
0Z
1R
0J
1B
1:
b0 0
b10111 1
b10111 !
b10111 .
b10111 /
04
07
15
0%
b10111 $
b10111 -
b10111 (
b0 *
b101110 )
b101010 &
b101010 +
#47
0=
1\
0U
1M
0E
1_
0X
1P
0H
0@
08
0;
1Z
0R
1J
0B
0:
03
b0 0
b101000 1
b101001 !
b101001 .
b101001 /
04
07
15
1%
b1 *
b101111 )
b10111 &
b10111 +
#48
0\
1U
0_
1X
0Z
1R
b11000 1
b11000 !
b11000 .
b11000 /
05
0%
b11000 $
b11000 -
b11000 (
b0 *
b110000 )
b101001 &
b101001 +
#49
1K
1D
1G
1C
1<
1?
1;
b111 0
14
1\
0U
1M
0E
0=
17
1_
0X
0P
1H
1@
18
1Z
0R
0J
1B
1:
13
b100111 1
b101000 !
b101000 .
b101000 /
05
1%
b1 *
b110001 )
b11000 &
b11000 +
#50
0[
0T
0W
0S
0K
0C
0L
0D
0<
0\
1U
1M
0O
0E
0G
0?
0_
1X
1P
0H
0@
0;
0Z
1R
1J
0B
0:
b0 0
b11001 1
b11001 !
b11001 .
b11001 /
04
07
15
0%
b11001 $
b11001 -
b11001 (
b0 *
b110010 )
b101000 &
b101000 +
#51
0K
0D
0G
1=
0C
0<
1\
0U
0M
1E
0?
1_
0X
0P
1H
1@
08
0;
1Z
0R
0J
1B
1:
03
b0 0
b100110 1
b100111 !
b100111 .
b100111 /
04
07
15
1%
b1 *
b110011 )
b11001 &
b11001 +
#52
0\
1U
1M
0E
0_
1X
1P
0H
0Z
1R
1J
0B
b11010 1
b11010 !
b11010 .
b11010 /
05
0%
b11010 $
b11010 -
b11010 (
b0 *
b110100 )
b100111 &
b100111 +
#53
1;
b1 0
14
1\
0U
0M
1E
1=
17
1_
0X
0P
1H
0@
18
1Z
0R
0J
1B
0:
13
b100101 1
b100110 !
b100110 .
b100110 /
05
1%
b1 *
b110101 )
b11010 &
b11010 +
#54
0\
1U
1M
0E
0_
1X
1P
0H
1@
0;
0Z
1R
1J
0B
1:
b0 0
b11011 1
b11011 !
b11011 .
b11011 /
04
07
15
0%
b11011 $
b11011 -
b11011 (
b0 *
b110110 )
b100110 &
b100110 +
#55
0=
1\
0U
0M
1E
1_
0X
0P
1H
0@
08
0;
1Z
0R
0J
1B
0:
03
b0 0
b100100 1
b100101 !
b100101 .
b100101 /
04
07
15
1%
b1 *
b110111 )
b11011 &
b11011 +
#56
0\
1U
1M
0_
1X
1P
0Z
1R
1J
b11100 1
b11100 !
b11100 .
b11100 /
05
0%
b11100 $
b11100 -
b11100 (
b0 *
b111000 )
b100101 &
b100101 +
#57
1C
1<
1?
1;
b11 0
14
1\
0U
0M
1E
0=
17
1_
0X
0P
0H
1@
18
1Z
0R
0J
0B
1:
13
b100011 1
b100100 !
b100100 .
b100100 /
05
1%
b1 *
b111001 )
b11100 &
b11100 +
#58
0[
0T
0W
0S
0L
0O
0K
0C
0D
0<
0\
1U
1M
1E
0G
0?
0_
1X
1P
1H
0@
0;
0Z
1R
1J
1B
0:
b0 0
b11101 1
b11101 !
b11101 .
b11101 /
04
07
15
0%
b11101 $
b11101 -
b11101 (
b0 *
b111010 )
b100100 &
b100100 +
#59
1=
0C
0<
1\
0U
0M
0E
0?
1_
0X
0P
0H
1@
08
0;
1Z
0R
0J
0B
1:
03
b0 0
b100010 1
b100011 !
b100011 .
b100011 /
04
07
15
1%
b1 *
b111011 )
b11101 &
b11101 +
#60
0\
1U
1M
1E
0_
1X
1P
1H
0Z
1R
1J
1B
b11110 1
b11110 !
b11110 .
b11110 /
05
0%
b11110 $
b11110 -
b11110 (
b0 *
b111100 )
b100011 &
b100011 +
#61
1;
b1 0
14
1\
0U
0M
0E
1=
17
1_
0X
0P
0H
0@
18
1Z
0R
0J
0B
0:
13
b100001 1
b100010 !
b100010 .
b100010 /
05
1%
b1 *
b111101 )
b11110 &
b11110 +
#62
0\
1U
1M
1E
0_
1X
1P
1H
1@
0;
0Z
1R
1J
1B
1:
b0 0
b11111 1
b11111 !
b11111 .
b11111 /
04
07
15
0%
b11111 $
b11111 -
b11111 (
b0 *
b111110 )
b100010 &
b100010 +
#63
0=
1\
0U
0M
0E
1_
0X
0P
0H
0@
08
0;
1Z
0R
0J
0B
0:
03
b0 0
b100000 1
b100001 !
b100001 .
b100001 /
04
07
15
1%
b1 *
b111111 )
b11111 &
b11111 +
#64
b100000 !
b100000 .
b100000 /
05
0%
b100000 $
b100000 -
b100000 (
b0 *
b1000000 )
b100001 &
b100001 +
#65
1[
1T
1W
1S
1L
1O
1K
1D
1G
1C
1<
1?
1;
b11111 0
14
1\
0U
0M
0E
0=
17
0_
1X
1P
1H
1@
18
0Z
1R
1J
1B
1:
13
b11111 1
b100000 !
b100000 .
b100000 /
05
1%
b1 *
b1000001 )
b100000 &
b100000 +
#66
0[
0S
0K
0C
0"
0T
0L
0D
0<
1\
0^
0U
0W
0M
0O
0E
0G
0?
1_
0X
0P
0H
0@
0;
1Z
0R
0J
0B
0:
b0 0
b100001 1
b100001 !
b100001 .
b100001 /
04
07
15
0%
b100001 $
b100001 -
b100001 (
b0 *
b1000010 )
#67
0[
0T
0W
0S
0L
0O
0K
0D
0G
1=
0C
0<
0\
1U
1M
1E
0?
0_
1X
1P
1H
1@
08
0;
0Z
1R
1J
1B
1:
03
b0 0
b11110 1
b11111 !
b11111 .
b11111 /
04
07
15
1%
b1 *
b1000011 )
b100001 &
b100001 +
#68
1\
0U
0M
0E
1_
0X
0P
0H
1Z
0R
0J
0B
b100010 1
b100010 !
b100010 .
b100010 /
05
0%
b100010 $
b100010 -
b100010 (
b0 *
b1000100 )
b11111 &
b11111 +
#69
1;
b1 0
14
0\
1U
1M
1E
1=
17
0_
1X
1P
1H
0@
18
0Z
1R
1J
1B
0:
13
b11101 1
b11110 !
b11110 .
b11110 /
05
1%
b1 *
b1000101 )
b100010 &
b100010 +
#70
1\
0U
0M
0E
1_
0X
0P
0H
1@
0;
1Z
0R
0J
0B
1:
b0 0
b100011 1
b100011 !
b100011 .
b100011 /
04
07
15
0%
b100011 $
b100011 -
b100011 (
b0 *
b1000110 )
b11110 &
b11110 +
#71
0=
0\
1U
1M
1E
0_
1X
1P
1H
0@
08
0;
0Z
1R
1J
1B
0:
03
b0 0
b11100 1
b11101 !
b11101 .
b11101 /
04
07
15
1%
b1 *
b1000111 )
b100011 &
b100011 +
#72
1\
0U
0M
1_
0X
0P
1Z
0R
0J
b100100 1
b100100 !
b100100 .
b100100 /
05
0%
b100100 $
b100100 -
b100100 (
b0 *
b1001000 )
b11101 &
b11101 +
#73
1C
1<
1?
1;
b11 0
14
0\
1U
1M
1E
0=
17
0_
1X
1P
0H
1@
18
0Z
1R
1J
0B
1:
13
b11011 1
b11100 !
b11100 .
b11100 /
05
1%
b1 *
b1001001 )
b100100 &
b100100 +
#74
0K
0C
0D
0<
1\
0U
0M
1E
0G
0?
1_
0X
0P
1H
0@
0;
1Z
0R
0J
1B
0:
b0 0
b100101 1
b100101 !
b100101 .
b100101 /
04
07
15
0%
b100101 $
b100101 -
b100101 (
b0 *
b1001010 )
b11100 &
b11100 +
#75
1=
0C
0<
0\
1U
1M
0E
0?
0_
1X
1P
0H
1@
08
0;
0Z
1R
1J
0B
1:
03
b0 0
b11010 1
b11011 !
b11011 .
b11011 /
04
07
15
1%
b1 *
b1001011 )
b100101 &
b100101 +
#76
1\
0U
0M
1E
1_
0X
0P
1H
1Z
0R
0J
1B
b100110 1
b100110 !
b100110 .
b100110 /
05
0%
b100110 $
b100110 -
b100110 (
b0 *
b1001100 )
b11011 &
b11011 +
#77
1;
b1 0
14
0\
1U
1M
0E
1=
17
0_
1X
1P
0H
0@
18
0Z
1R
1J
0B
0:
13
b11001 1
b11010 !
b11010 .
b11010 /
05
1%
b1 *
b1001101 )
b100110 &
b100110 +
#78
1\
0U
0M
1E
1_
0X
0P
1H
1@
0;
1Z
0R
0J
1B
1:
b0 0
b100111 1
b100111 !
b100111 .
b100111 /
04
07
15
0%
b100111 $
b100111 -
b100111 (
b0 *
b1001110 )
b11010 &
b11010 +
#79
0=
0\
1U
1M
0E
0_
1X
1P
0H
0@
08
0;
0Z
1R
1J
0B
0:
03
b0 0
b11000 1
b11001 !
b11001 .
b11001 /
04
07
15
1%
b1 *
b1001111 )
b100111 &
b100111 +
#80
1\
0U
1_
0X
1Z
0R
b101000 1
b101000 !
b101000 .
b101000 /
05
0%
b101000 $
b101000 -
b101000 (
b0 *
b1010000 )
b11001 &
b11001 +
#81
1K
1D
1G
1C
1<
1?
1;
b111 0
14
0\
1U
1M
0E
0=
17
0_
1X
0P
1H
1@
18
0Z
1R
0J
1B
1:
13
b10111 1
b11000 !
b11000 .
b11000 /
05
1%
b1 *
b1010001 )
b101000 &
b101000 +
#82
0S
0K
0C
0L
0D
0<
1\
0U
1M
0O
0E
0G
0?
1_
0X
1P
0H
0@
0;
1Z
0R
1J
0B
0:
b0 0
b101001 1
b101001 !
b101001 .
b101001 /
04
07
15
0%
b101001 $
b101001 -
b101001 (
b0 *
b1010010 )
b11000 &
b11000 +
#83
0K
0D
0G
1=
0C
0<
0\
1U
0M
1E
0?
0_
1X
0P
1H
1@
08
0;
0Z
1R
0J
1B
1:
03
b0 0
b10110 1
b10111 !
b10111 .
b10111 /
04
07
15
1%
b1 *
b1010011 )
b101001 &
b101001 +
#84
1\
0U
1M
0E
1_
0X
1P
0H
1Z
0R
1J
0B
b101010 1
b101010 !
b101010 .
b101010 /
05
0%
b101010 $
b101010 -
b101010 (
b0 *
b1010100 )
b10111 &
b10111 +
#85
1;
b1 0
14
0\
1U
0M
1E
1=
17
0_
1X
0P
1H
0@
18
0Z
1R
0J
1B
0:
13
b10101 1
b10110 !
b10110 .
b10110 /
05
1%
b1 *
b1010101 )
b101010 &
b101010 +
#86
1\
0U
1M
0E
1_
0X
1P
0H
1@
0;
1Z
0R
1J
0B
1:
b0 0
b101011 1
b101011 !
b101011 .
b101011 /
04
07
15
0%
b101011 $
b101011 -
b101011 (
b0 *
b1010110 )
b10110 &
b10110 +
#87
0=
0\
1U
0M
1E
0_
1X
0P
1H
0@
08
0;
0Z
1R
0J
1B
0:
03
b0 0
b10100 1
b10101 !
b10101 .
b10101 /
04
07
15
1%
b1 *
b1010111 )
b101011 &
b101011 +
#88
1\
0U
1M
1_
0X
1P
1Z
0R
1J
b101100 1
b101100 !
b101100 .
b101100 /
05
0%
b101100 $
b101100 -
b101100 (
b0 *
b1011000 )
b10101 &
b10101 +
#89
1C
1<
1?
1;
b11 0
14
0\
1U
0M
1E
0=
17
0_
1X
0P
0H
1@
18
0Z
1R
0J
0B
1:
13
b10011 1
b10100 !
b10100 .
b10100 /
05
1%
b1 *
b1011001 )
b101100 &
b101100 +
#90
0S
0L
0O
0K
0C
0D
0<
1\
0U
1M
1E
0G
0?
1_
0X
1P
1H
0@
0;
1Z
0R
1J
1B
0:
b0 0
b101101 1
b101101 !
b101101 .
b101101 /
04
07
15
0%
b101101 $
b101101 -
b101101 (
b0 *
b1011010 )
b10100 &
b10100 +
