entrega/simulation/generated/somador_1bit.v
// Copyright (C) 2021  Intel Corporation. All rights reserved.
// Your use of Intel Corporation's design tools, logic functions 
// and other software and tools, and any partner logic 
// functions, and any output files from any of the foregoing 
// (including device programming or simulation files), and any 
// associated documentation or information are expressly subject 
// to the terms and conditions of the Intel Program License 
// Subscription Agreement, the Intel Quartus Prime License Agreement,
// the Intel FPGA IP License Agreement, or other applicable license
// agreement, including, without limitation, that your use is for
// the sole purpose of programming logic devices manufactured by
// Intel and sold by Intel or its authorized distributors.  Please
// refer to the applicable agreement for further details, at
// https://fpgasoftware.intel.com/eula.


module somador_1bit(
	A,
	B,
	Cin,
	S,
	Cout
);


input wire	A;
input wire	B;
input wire	Cin;
output wire	S;
output wire	Cout;

wire	fa_G;
wire	fa_H;
wire	fa_P;




assign	fa_G = A & B;

assign	fa_H = fa_P & Cin;

assign	Cout = fa_H | fa_G;

assign	fa_P = A ^ B;

assign	S = fa_P ^ Cin;


endmodule

entrega/simulation/generated/somador_subtrator_5bit.v
// Copyright (C) 2021  Intel Corporation. All rights reserved.
// Your use of Intel Corporation's design tools, logic functions 
// and other software and tools, and any partner logic 
// functions, and any output files from any of the foregoing 
// (including device programming or simulation files), and any 
// associated documentation or information are expressly subject 
// to the terms and conditions of the Intel Program License 
// Subscription Agreement, the Intel Quartus Prime License Agreement,
// the Intel FPGA IP License Agreement, or other applicable license
// agreement, including, without limitation, that your use is for
// the sole purpose of programming logic devices manufactured by
// Intel and sold by Intel or its authorized distributors.  Please
// refer to the applicable agreement for further details, at
// https://fpgasoftware.intel.com/eula.


module somador_subtrator_5bit(
	SUB,
	A,
	B,
	Cout,
	R
);


input wire	SUB;
input wire	[4:0] A;
input wire	[4:0] B;
output wire	Cout;
output wire	[4:0] R;

wire	[4:0] BX;
wire	[4:1] CARRY;
wire	[4:0] R_ALTERA_SYNTHESIZED;





somador_1bit	b2v_fa_0(
	.A(A[0]),
	.B(BX[0]),
	.Cin(SUB),
	.S(R_ALTERA_SYNTHESIZED[0]),
	.Cout(CARRY[1]));


somador_1bit	b2v_fa_1(
	.A(A[1]),
	.B(BX[1]),
	.Cin(CARRY[1]),
	.S(R_ALTERA_SYNTHESIZED[1]),
	.Cout(CARRY[2]));


somador_1bit	b2v_fa_2(
	.A(A[2]),
	.B(BX[2]),
	.Cin(CARRY[2]),
	.S(R_ALTERA_SYNTHESIZED[2]),
	.Cout(CARRY[3]));


somador_1bit	b2v_fa_3(
	.A(A[3]),
	.B(BX[3]),
	.Cin(CARRY[3]),
	.S(R_ALTERA_SYNTHESIZED[3]),
	.Cout(CARRY[4]));


somador_1bit	b2v_fa_4(
	.A(A[4]),
	.B(BX[4]),
	.Cin(CARRY[4]),
	.S(R_ALTERA_SYNTHESIZED[4]),
	.Cout(Cout));

assign	BX[0] = B[0] ^ SUB;

assign	BX[1] = B[1] ^ SUB;

assign	BX[2] = B[2] ^ SUB;

assign	BX[3] = B[3] ^ SUB;

assign	BX[4] = B[4] ^ SUB;

assign	R = R_ALTERA_SYNTHESIZED;

endmodule

entrega/simulation/tb_somador_subtrator_5bit.sv
module tb_somador_subtrator_5bit;
reg [4:0] A;
reg [4:0] B;
reg SUB;
wire [4:0] R;
wire Cout;
integer a;
integer b;
integer sub;
integer total;
integer checks;
reg [5:0] expected;
somador_subtrator_5bit dut(.A(A),.B(B),.SUB(SUB),.R(R),.Cout(Cout));
initial begin
  $dumpfile("waveforms/somador_subtrator_5bit.vcd");
  $dumpvars(0,tb_somador_subtrator_5bit);
  checks=0;
  for(a=0;a<32;a=a+1) begin
    for(b=0;b<32;b=b+1) begin
      for(sub=0;sub<2;sub=sub+1) begin
        A=a; B=b; SUB=sub; #1;
        total=a+(b ^ (sub ? 31 : 0))+sub;
        expected=total;
        if({Cout,R} !== expected) $fatal(1,"A=%0d B=%0d SUB=%0d obtido=%b esperado=%b",a,b,sub,{Cout,R},expected);
        checks=checks+1;
      end
    end
  end
  if(checks!=2048) $fatal(1,"cobertura incompleta: %0d",checks);
  $display("tb_somador_subtrator_5bit PASS checks=%0d",checks);
  $finish;
end
endmodule

entrega/simulation/waveforms/somador_subtrator_5bit.vcd
$date
	Wed Sep 30 02:06:35 2026
$end
$version
	Icarus Verilog
$end
$timescale
	1s
$end
$scope module tb_somador_subtrator_5bit $end
$var wire 5 ! R [4:0] $end
$var wire 1 " Cout $end
$var reg 5 # A [4:0] $end
$var reg 5 $ B [4:0] $end
$var reg 1 % SUB $end
$var reg 6 & expected [5:0] $end
$var integer 32 ' a [31:0] $end
$var integer 32 ( b [31:0] $end
$var integer 32 ) checks [31:0] $end
$var integer 32 * sub [31:0] $end
$var integer 32 + total [31:0] $end
$scope module dut $end
$var wire 5 , A [4:0] $end
$var wire 5 - B [4:0] $end
$var wire 5 . R [4:0] $end
$var wire 1 % SUB $end
$var wire 5 / R_ALTERA_SYNTHESIZED [4:0] $end
$var wire 1 " Cout $end
$var wire 4 0 CARRY [4:1] $end
$var wire 5 1 BX [4:0] $end
$scope module b2v_fa_0 $end
$var wire 1 2 A $end
$var wire 1 3 B $end
$var wire 1 % Cin $end
$var wire 1 4 Cout $end
$var wire 1 5 S $end
$var wire 1 6 fa_G $end
$var wire 1 7 fa_H $end
$var wire 1 8 fa_P $end
$upscope $end
$scope module b2v_fa_1 $end
$var wire 1 9 A $end
$var wire 1 : B $end
$var wire 1 ; Cin $end
$var wire 1 < Cout $end
$var wire 1 = S $end
$var wire 1 > fa_G $end
$var wire 1 ? fa_H $end
$var wire 1 @ fa_P $end
$upscope $end
$scope module b2v_fa_2 $end
$var wire 1 A A $end
$var wire 1 B B $end
$var wire 1 C Cin $end
$var wire 1 D Cout $end
$var wire 1 E S $end
$var wire 1 F fa_G $end
$var wire 1 G fa_H $end
$var wire 1 H fa_P $end
$upscope $end
$scope module b2v_fa_3 $end
$var wire 1 I A $end
$var wire 1 J B $end
$var wire 1 K Cin $end
$var wire 1 L Cout $end
$var wire 1 M S $end
$var wire 1 N fa_G $end
$var wire 1 O fa_H $end
$var wire 1 P fa_P $end
$upscope $end
$scope module b2v_fa_4 $end
$var wire 1 Q A $end
$var wire 1 R B $end
$var wire 1 S Cin $end
$var wire 1 " Cout $end
$var wire 1 T S $end
$var wire 1 U fa_G $end
$var wire 1 V fa_H $end
$var wire 1 W fa_P $end
$upscope $end
$upscope $end
$upscope $end
$enddefinitions $end
$comment Show the parameter values. $end
$dumpall
$end
#0
$dumpvars
0W
0V
0U
0T
0S
0R
0Q
0P
0O
0N
0M
0L
0K
0J
0I
0H
0G
0F
0E
0D
0C
0B
0A
0@
0?
0>
0=
0<
0;
0:
09
08
07
06
05
04
03
02
b0 1
b0 0
b0 /
b0 .
b0 -
b0 ,
bx +
b0 *
b0 )
b0 (
b0 '
bx &
0%
b0 $
b0 #
0"
b0 !
$end
#1
1"
1V
1S
1L
1O
1K
1D
1G
1C
1<
1?
1;
b1111 0
14
0T
0M
0E
0=
17
1W
1P
1H
1@
18
1R
1J
1B
1:
13
b11111 1
b0 !
b0 .
b0 /
05
1%
b1 *
b1 )
b0 &
b0 +
#2
0S
0K
0C
0"
0L
0D
0T
0V
0M
0O
0E
0G
0<
0W
0P
0H
0@
0?
0=
0R
0J
0B
0:
0;
b1 1
b0 0
b1 !
b1 .
b1 /
04
07
15
0%
b1 $
b1 -
b1 (
b0 *
b10 )
b100000 &
b100000 +
#3
0"
0V
0S
0L
0O
0K
0D
0G
0C
0<
1T
1M
1E
0?
1W
1P
1H
1@
08
1=
1R
1J
1B
1:
03
0;
b11110 1
b0 0
b11111 !
b11111 .
b11111 /
04
07
15
1%
b1 *
b11 )
b1 &
b1 +
#4
0T
0M
0E
0W
0P
0H
0R
0J
0B
b10 1
b10 !
b10 .
b10 /
05
0%
b10 $
b10 -
b10 (
b0 *
b100 )
b11111 &
b11111 +
#5
1;
b1 0
14
1T
1M
1E
1=
17
1W
1P
1H
0@
18
1R
1J
1B
0:
13
b11101 1
b11110 !
b11110 .
b11110 /
05
1%
b1 *
b101 )
b10 &
b10 +
#6
0T
0M
0E
0W
0P
0H
1@
1=
0R
0J
0B
1:
0;
b11 1
b0 0
b11 !
b11 .
b11 /
04
07
15
0%
b11 $
b11 -
b11 (
b0 *
b110 )
b11110 &
b11110 +
#7
0"
0V
0S
0L
0O
0K
0D
0G
0C
1T
1M
1E
0<
1W
1P
1H
0@
08
0?
0=
1R
1J
1B
0:
03
0;
b11100 1
b0 0
b11101 !
b11101 .
b11101 /
04
07
15
1%
b1 *
b111 )
b11 &
b11 +
#8
0T
0M
0W
0P
0R
0J
b100 1
b100 !
b100 .
b100 /
05
0%
b100 $
b100 -
b100 (
b0 *
b1000 )
b11101 &
b11101 +
#9
1C
1<
1?
1;
b11 0
14
1T
1M
1E
0=
17
1W
1P
0H
1@
18
1R
1J
0B
1:
13
b11011 1
b11100 !
b11100 .
b11100 /
05
1%
b1 *
b1001 )
b100 &
b100 +
#10
0K
0C
0D
0T
0M
1E
0G
0<
0W
0P
1H
0@
0?
0=
0R
0J
1B
0:
0;
b101 1
b0 0
b101 !
b101 .
b101 /
04
07
15
0%
b101 $
b101 -
b101 (
b0 *
b1010 )
b11100 &
b11100 +
#11
0C
0<
1T
1M
0E
0?
1W
1P
0H
1@
08
1=
1R
1J
0B
1:
03
0;
b11010 1
b0 0
b11011 !
b11011 .
b11011 /
04
07
15
1%
b1 *
b1011 )
b101 &
b101 +
#12
0T
0M
1E
0W
0P
1H
0R
0J
1B
b110 1
b110 !
b110 .
b110 /
05
0%
b110 $
b110 -
b110 (
b0 *
b1100 )
b11011 &
b11011 +
#13
1;
b1 0
14
1T
1M
0E
1=
17
1W
1P
0H
0@
18
1R
1J
0B
0:
13
b11001 1
b11010 !
b11010 .
b11010 /
05
1%
b1 *
b1101 )
b110 &
b110 +
#14
0T
0M
1E
0W
0P
1H
1@
1=
0R
0J
1B
1:
0;
b111 1
b0 0
b111 !
b111 .
b111 /
04
07
15
0%
b111 $
b111 -
b111 (
b0 *
b1110 )
b11010 &
b11010 +
#15
0C
1T
1M
0E
0<
1W
1P
0H
0@
08
0?
0=
1R
1J
0B
0:
03
0;
b11000 1
b0 0
b11001 !
b11001 .
b11001 /
04
07
15
1%
b1 *
b1111 )
b111 &
b111 +
#16
0T
0W
0R
b1000 1
b1000 !
b1000 .
b1000 /
05
0%
b1000 $
b1000 -
b1000 (
b0 *
b10000 )
b11001 &
b11001 +
#17
1K
1D
1G
1C
1<
1?
1;
b111 0
14
1T
1M
0E
0=
17
1W
0P
1H
1@
18
1R
0J
1B
1:
13
b10111 1
b11000 !
b11000 .
b11000 /
05
1%
b1 *
b10001 )
b1000 &
b1000 +
#18
0S
0K
0C
0L
0D
0T
1M
0O
0E
0G
0<
0W
1P
0H
0@
0?
0=
0R
1J
0B
0:
0;
b1001 1
b0 0
b1001 !
b1001 .
b1001 /
04
07
15
0%
b1001 $
b1001 -
b1001 (
b0 *
b10010 )
b11000 &
b11000 +
#19
0K
0D
0G
0C
0<
1T
0M
1E
0?
1W
0P
1H
1@
08
1=
1R
0J
1B
1:
03
0;
b10110 1
b0 0
b10111 !
b10111 .
b10111 /
04
07
15
1%
b1 *
b10011 )
b1001 &
b1001 +
#20
0T
1M
0E
0W
1P
0H
0R
1J
0B
b1010 1
b1010 !
b1010 .
b1010 /
05
0%
b1010 $
b1010 -
b1010 (
b0 *
b10100 )
b10111 &
b10111 +
#21
1;
b1 0
14
1T
0M
1E
1=
17
1W
0P
1H
0@
18
1R
0J
1B
0:
13
b10101 1
b10110 !
b10110 .
b10110 /
05
1%
b1 *
b10101 )
b1010 &
b1010 +
#22
0T
1M
0E
0W
1P
0H
1@
1=
0R
1J
0B
1:
0;
b1011 1
b0 0
b1011 !
b1011 .
b1011 /
04
07
15
0%
b1011 $
b1011 -
b1011 (
b0 *
b10110 )
b10110 &
b10110 +
#23
0K
0D
0G
0C
1T
0M
1E
0<
1W
0P
1H
0@
08
0?
0=
1R
0J
1B
0:
03
0;
b10100 1
b0 0
b10101 !
b10101 .
b10101 /
04
07
15
1%
b1 *
b10111 )
b1011 &
b1011 +
#24
0T
1M
0W
1P
0R
1J
b1100 1
b1100 !
b1100 .
b1100 /
05
0%
b1100 $
b1100 -
b1100 (
b0 *
b11000 )
b10101 &
b10101 +
#25
1C
1<
1?
1;
b11 0
14
1T
0M
1E
0=
17
1W
0P
0H
1@
18
1R
0J
0B
1:
13
b10011 1
b10100 !
b10100 .
b10100 /
05
1%
b1 *
b11001 )
b1100 &
b1100 +
#26
0S
0L
0O
0K
0C
0D
0T
1M
1E
0G
0<
0W
1P
1H
0@
0?
0=
0R
1J
1B
0:
0;
b1101 1
b0 0
b1101 !
b1101 .
b1101 /
04
07
15
0%
b1101 $
b1101 -
b1101 (
b0 *
b11010 )
b10100 &
b10100 +
#27
0C
0<
1T
0M
0E
0?
1W
0P
0H
1@
08
1=
1R
0J
0B
1:
03
0;
b10010 1
b0 0
b10011 !
b10011 .
b10011 /
04
07
15
1%
b1 *
b11011 )
b1101 &
b1101 +
#28
0T
1M
1E
0W
1P
1H
0R
1J
1B
b1110 1
b1110 !
b1110 .
b1110 /
05
0%
b1110 $
b1110 -
b1110 (
b0 *
b11100 )
b10011 &
b10011 +
#29
1;
b1 0
14
1T
0M
0E
1=
17
1W
0P
0H
0@
18
1R
0J
0B
0:
13
b10001 1
b10010 !
b10010 .
b10010 /
05
1%
b1 *
b11101 )
b1110 &
b1110 +
#30
0T
1M
1E
0W
1P
1H
1@
1=
0R
1J
1B
1:
0;
b1111 1
b0 0
b1111 !
b1111 .
b1111 /
04
07
15
0%
b1111 $
b1111 -
b1111 (
b0 *
b11110 )
b10010 &
b10010 +
#31
0C
1T
0M
0E
0<
1W
0P
0H
0@
08
0?
0=
1R
0J
0B
0:
03
0;
b10000 1
b0 0
b10001 !
b10001 .
b10001 /
04
07
15
1%
b1 *
b11111 )
b1111 &
b1111 +
#32
b10000 !
b10000 .
b10000 /
05
0%
b10000 $
b10000 -
b10000 (
b0 *
b100000 )
b10001 &
b10001 +
#33
1S
1L
1O
1K
1D
1G
1C
1<
1?
1;
b1111 0
14
1T
0M
0E
0=
17
0W
1P
1H
1@
18
0R
1J
1B
1:
13
b1111 1
b10000 !
b10000 .
b10000 /
05
1%
b1 *
b100001 )
b10000 &
b10000 +
#34
0S
0K
0C
0"
0L
0D
1T
0V
0M
0O
0E
0G
0<
1W
0P
0H
0@
0?
0=
1R
0J
0B
0:
0;
b10001 1
b0 0
b10001 !
b10001 .
b10001 /
04
07
15
0%
b10001 $
b10001 -
b10001 (
b0 *
b100010 )
#35
0S
0L
0O
0K
0D
0G
0C
0<
0T
1M
1E
0?
0W
1P
1H
1@
08
1=
0R
1J
1B
1:
03
0;
b1110 1
b0 0
b1111 !
b1111 .
b1111 /
04
07
15
1%
b1 *
b100011 )
b10001 &
b10001 +
#36
1T
0M
0E
1W
0P
0H
1R
0J
0B
b10010 1
b10010 !
b10010 .
b10010 /
05
0%
b10010 $
b10010 -
b10010 (
b0 *
b100100 )
b1111 &
b1111 +
#37
1;
b1 0
14
0T
1M
1E
1=
17
0W
1P
1H
0@
18
0R
1J
1B
0:
13
b1101 1
b1110 !
b1110 .
b1110 /
05
1%
b1 *
b100101 )
b10010 &
b10010 +
#38
1T
0M
0E
1W
0P
0H
1@
1=
1R
0J
0B
1:
0;
b10011 1
b0 0
b10011 !
b10011 .
b10011 /
04
07
15
0%
b10011 $
b10011 -
b10011 (
b0 *
b100110 )
b1110 &
b1110 +
#39
0S
0L
0O
0K
0D
0G
0C
0T
1M
1E
0<
0W
1P
1H
0@
08
0?
0=
0R
1J
1B
0:
03
0;
b1100 1
b0 0
b1101 !
b1101 .
b1101 /
04
07
15
1%
b1 *
b100111 )
b10011 &
b10011 +
#40
1T
0M
1W
0P
1R
0J
b10100 1
b10100 !
b10100 .
b10100 /
05
0%
b10100 $
b10100 -
b10100 (
b0 *
b101000 )
b1101 &
b1101 +
#41
1C
1<
1?
1;
b11 0
14
0T
1M
1E
0=
17
0W
1P
0H
1@
18
0R
1J
0B
1:
13
b1011 1
b1100 !
b1100 .
b1100 /
05
1%
b1 *
b101001 )
b10100 &
b10100 +
#42
0K
0C
0D
1T
0M
1E
0G
0<
1W
0P
1H
0@
0?
0=
1R
0J
1B
0:
0;
b10101 1
b0 0
b10101 !
b10101 .
b10101 /
04
07
15
0%
b10101 $
b10101 -
b10101 (
b0 *
b101010 )
b1100 &
b1100 +
#43
0C
0<
0T
1M
0E
0?
0W
1P
0H
1@
08
1=
0R
1J
0B
1:
03
0;
b1010 1
b0 0
b1011 !
b1011 .
b1011 /
04
07
15
1%
b1 *
b101011 )
b10101 &
b10101 +
#44
1T
0M
1E
1W
0P
1H
1R
0J
1B
b10110 1
b10110 !
b10110 .
b10110 /
05
0%
b10110 $
b10110 -
b10110 (
b0 *
b101100 )
b1011 &
b1011 +
#45
1;
b1 0
14
0T
1M
0E
1=
17
0W
1P
0H
0@
18
0R
1J
0B
0:
13
b1001 1
b1010 !
b1010 .
b1010 /
05
1%
b1 *
b101101 )
b10110 &
b10110 +
#46
1T
0M
1E
1W
0P
1H
1@
1=
1R
0J
1B
1:
0;
b10111 1
b0 0
b10111 !
b10111 .
b10111 /
04
07
15
0%
b10111 $
b10111 -
b10111 (
b0 *
b101110 )
b1010 &
b1010 +
#47
0C
0T
1M
0E
0<
0W
1P
0H
0@
08
0?
0=
0R
1J
0B
0:
03
0;
b1000 1
b0 0
b1001 !
b1001 .
b1001 /
04
07
15
1%
b1 *
b101111 )
b10111 &
b10111 +
#48
1T
1W
1R
b11000 1
b11000 !
b11000 .
b11000 /
05
0%
b11000 $
b11000 -
b11000 (
b0 *
b110000 )
b1001 &
b1001 +
#49
1K
1D
1G
1C
1<
1?
1;
b111 0
14
0T
1M
0E
0=
17
0W
0P
1H
1@
18
0R
0J
1B
1:
13
b111 1
b1000 !
b1000 .
b1000 /
05
1%
b1 *
b110001 )
b11000 &
b11000 +
#50
0"
0V
0S
0K
0C
0L
0D
1T
1M
0O
0E
0G
0<
1W
1P
0H
0@
0?
0=
1R
1J
0B
0:
0;
b11001 1
b0 0
b11001 !
b11001 .
b11001 /
04
07
15
0%
b11001 $
b11001 -
b11001 (
b0 *
b110010 )
b1000 &
b1000 +
#51
0K
0D
0G
0C
0<
0T
0M
1E
0?
0W
0P
1H
1@
08
1=
0R
0J
1B
1:
03
0;
b110 1
b0 0
b111 !
b111 .
b111 /
04
07
15
1%
b1 *
b110011 )
b11001 &
b11001 +
#52
1T
1M
0E
1W
1P
0H
1R
1J
0B
b11010 1
b11010 !
b11010 .
b11010 /
05
0%
b11010 $
b11010 -
b11010 (
b0 *
b110100 )
b111 &
b111 +
#53
1;
b1 0
14
0T
0M
1E
1=
17
0W
0P
1H
0@
18
0R
0J
1B
0:
13
b101 1
b110 !
b110 .
b110 /
05
1%
b1 *
b110101 )
b11010 &
b11010 +
#54
1T
1M
0E
1W
1P
0H
1@
1=
1R
1J
0B
1:
0;
b11011 1
b0 0
b11011 !
b11011 .
b11011 /
04
07
15
0%
b11011 $
b11011 -
b11011 (
b0 *
b110110 )
b110 &
b110 +
#55
0K
0D
0G
0C
0T
0M
1E
0<
0W
0P
1H
0@
08
0?
0=
0R
0J
1B
0:
03
0;
b100 1
b0 0
b101 !
b101 .
b101 /
04
07
15
1%
b1 *
b110111 )
b11011 &
b11011 +
#56
1T
1M
1W
1P
1R
1J
b11100 1
b11100 !
b11100 .
b11100 /
05
0%
b11100 $
b11100 -
b11100 (
b0 *
b111000 )
b101 &
b101 +
#57
1C
1<
1?
1;
b11 0
14
0T
0M
1E
0=
17
0W
0P
0H
1@
18
0R
0J
0B
1:
13
b11 1
b100 !
b100 .
b100 /
05
1%
b1 *
b111001 )
b11100 &
b11100 +
#58
0"
0V
0S
0L
0O
0K
0C
0D
1T
1M
1E
0G
0<
1W
1P
1H
0@
0?
0=
1R
1J
1B
0:
0;
b11101 1
b0 0
b11101 !
b11101 .
b11101 /
04
07
15
0%
b11101 $
b11101 -
b11101 (
b0 *
b111010 )
b100 &
b100 +
#59
0C
0<
0T
0M
0E
0?
0W
0P
0H
1@
08
1=
0R
0J
0B
1:
03
0;
b10 1
b0 0
b11 !
b11 .
b11 /
04
07
15
1%
b1 *
b111011 )
b11101 &
b11101 +
#60
1T
1M
1E
1W
1P
1H
1R
1J
1B
b11110 1
b11110 !
b11110 .
b11110 /
05
0%
b11110 $
b11110 -
b11110 (
b0 *
b111100 )
b11 &
b11 +
#61
1;
b1 0
14
0T
0M
0E
1=
17
0W
0P
0H
0@
18
0R
0J
0B
0:
13
b1 1
b10 !
b10 .
b10 /
05
1%
b1 *
b111101 )
b11110 &
b11110 +
#62
1T
1M
1E
1W
1P
1H
1@
1=
1R
1J
1B
1:
0;
b11111 1
b0 0
b11111 !
b11111 .
b11111 /
04
07
15
0%
b11111 $
b11111 -
b11111 (
b0 *
b111110 )
b10 &
b10 +
#63
0C
0T
0M
0E
0<
0W
0P
0H
0@
08
0?
0=
0R
0J
0B
0:
03
0;
b0 1
b0 0
b1 !
b1 .
b1 /
04
07
15
1%
b1 *
b111111 )
b11111 &
b11111 +
#64
b1 !
b1 .
b1 /
18
15
12
0%
b0 $
b0 -
b1 #
b1 ,
b1 '
b0 (
b0 *
b1000000 )
b1 &
b1 +
#65
1"
1V
1S
1L
1O
1K
1D
1G
1C
1<
0T
0M
0E
1?
1W
1P
1H
1@
16
08
0=
1R
1J
1B
1:
13
1;
b11111 1
b1111 0
b1 !
b1 .
b1 /
14
07
15
1%
b1 *
b1000001 )
#66
0S
0K
0C
b1 0
0"
0L
0D
0<
0T
0V
0M
0O
0E
0G
1=
0?
0W
0P
0H
0@
0R
0J
0B
0:
b1 1
b10 !
b10 .
b10 /
05
0%
b1 $
b1 -
b1 (
b0 *
b1000010 )
b100001 &
b100001 +
#67
1"
1V
1S
1L
1O
1K
1D
1G
1C
b1111 0
1<
0T
0M
0E
0=
1?
17
1W
1P
1H
1@
06
18
1R
1J
1B
1:
03
b11110 1
b0 !
b0 .
b0 /
05
1%
b1 *
b1000011 )
b10 &
b10 +
#68
0S
0K
0C
0"
0L
0D
0T
0V
0M
0O
0E
0G
0<
0W
0P
0H
0?
1=
0R
0J
0B
0;
b10 1
b0 0
b11 !
b11 .
b11 /
04
07
15
0%
b10 $
b10 -
b10 (
b0 *
b1000100 )
b100000 &
b100000 +
#69
0"
0V
0S
0L
0O
0K
0D
0G
0C
1T
1M
1E
0<
1W
1P
1H
0@
16
08
0?
1=
1R
1J
1B
0:
13
1;
b11101 1
b1 0
b11111 !
b11111 .
b11111 /
14
07
15
1%
b1 *
b1000101 )
b11 &
b11 +
#70
1C
b11 0
1<
0T
0M
1E
0=
1?
0W
0P
0H
1@
0R
0J
0B
1:
b11 1
b100 !
b100 .
b100 /
05
0%
b11 $
b11 -
b11 (
b0 *
b1000110 )
b11111 &
b11111 +
#71
0"
0V
0S
0L
0O
0K
0C
b1 0
0D
0<
1T
1M
1E
0G
1=
0?
17
1W
1P
1H
0@
06
18
1R
1J
1B
0:
03
b11100 1
b11110 !
b11110 .
b11110 /
05
1%
b1 *
b1000111 )
b100 &
b100 +
#72
0T
0M
0W
0P
0=
0R
0J
0;
b100 1
b0 0
b101 !
b101 .
b101 /
04
07
15
0%
b100 $
b100 -
b100 (
b0 *
b1001000 )
b11110 &
b11110 +
#73
1C
1<
1T
1M
1E
1?
1W
1P
0H
1@
16
08
0=
1R
1J
0B
1:
13
1;
b11011 1
b11 0
b11101 !
b11101 .
b11101 /
14
07
15
1%
b1 *
b1001001 )
b101 &
b101 +
#74
0K
0C
b1 0
0D
0<
0T
0M
1E
0G
1=
0?
0W
0P
1H
0@
0R
0J
1B
0:
b101 1
b110 !
b110 .
b110 /
05
0%
b101 $
b101 -
b101 (
b0 *
b1001010 )
b11101 &
b11101 +
#75
1C
b11 0
1<
1T
1M
1E
0=
1?
17
1W
1P
0H
1@
06
18
1R
1J
0B
1:
03
b11010 1
b11100 !
b11100 .
b11100 /
05
1%
b1 *
b1001011 )
b110 &
b110 +
#76
0K
0C
0D
0T
0M
1E
0G
0<
0W
0P
1H
0?
1=
0R
0J
1B
0;
b110 1
b0 0
b111 !
b111 .
b111 /
04
07
15
0%
b110 $
b110 -
b110 (
b0 *
b1001100 )
b11100 &
b11100 +
#77
0C
1T
1M
0E
0<
1W
1P
0H
0@
16
08
0?
1=
1R
1J
0B
0:
13
1;
b11001 1
b1 0
b11011 !
b11011 .
b11011 /
14
07
15
1%
b1 *
b1001101 )
b111 &
b111 +
#78
1K
1D
1G
1C
b111 0
1<
0T
1M
0E
0=
1?
0W
0P
1H
1@
0R
0J
1B
1:
b111 1
b1000 !
b1000 .
b1000 /
05
0%
b111 $
b111 -
b111 (
b0 *
b1001110 )
b11011 &
b11011 +
#79
0"
0V
0S
0K
0C
b1 0
0L
0D
0<
1T
1M
0O
0E
0G
1=
0?
17
1W
1P
0H
0@
06
18
1R
1J
0B
0:
03
b11000 1
b11010 !
b11010 .
b11010 /
05
1%
b1 *
b1001111 )
b1000 &
b1000 +
#80
0T
0W
0=
0R
0;
b1000 1
b0 0
b1001 !
b1001 .
b1001 /
04
07
15
0%
b1000 $
b1000 -
b1000 (
b0 *
b1010000 )
b11010 &
b11010 +
#81
1K
1D
1G
1C
1<
1T
1M
0E
1?
1W
0P
1H
1@
16
08
0=
1R
0J
1B
1:
13
1;
b10111 1
b111 0
b11001 !
b11001 .
b11001 /
14
07
15
1%
b1 *
b1010001 )
b1001 &
b1001 +
#82
0S
0K
0C
b1 0
0L
0D
0<
0T
1M
0O
0E
0G
1=
0?
0W
1P
0H
0@
0R
1J
0B
0:
b1001 1
b1010 !
b1010 .
b1010 /
05
0%
b1001 $
b1001 -
b1001 (
b0 *
b1010010 )
b11001 &
b11001 +
#83
1K
1D
1G
1C
b111 0
1<
1T
1M
0E
0=
1?
17
1W
0P
1H
1@
06
18
1R
0J
1B
1:
03
b10110 1
b11000 !
b11000 .
b11000 /
05
1%
b1 *
b1010011 )
b1010 &
b1010 +
#84
0S
0K
0C
0L
0D
0T
1M
0O
0E
0G
0<
0W
1P
0H
0?
1=
0R
1J
0B
0;
b1010 1
b0 0
b1011 !
b1011 .
b1011 /
04
07
15
0%
b1010 $
b1010 -
b1010 (
b0 *
b1010100 )
b11000 &
b11000 +
#85
0K
0D
0G
0C
1T
0M
1E
0<
1W
0P
1H
0@
16
08
0?
1=
1R
0J
1B
0:
13
1;
b10101 1
b1 0
b10111 !
b10111 .
b10111 /
14
07
15
1%
b1 *
b1010101 )
b1011 &
b1011 +
#86
1C
b11 0
1<
0T
1M
1E
0=
1?
0W
1P
0H
1@
0R
1J
0B
1:
b1011 1
b1100 !
b1100 .
b1100 /
05
0%
b1011 $
b1011 -
b1011 (
b0 *
b1010110 )
b10111 &
b10111 +
#87
0K
0C
b1 0
0D
0<
1T
0M
1E
0G
1=
0?
17
1W
0P
1H
0@
06
18
1R
0J
1B
0:
03
b10100 1
b10110 !
b10110 .
b10110 /
05
1%
b1 *
b1010111 )
b1100 &
b1100 +
#88
0T
1M
0W
1P
0=
0R
1J
0;
b1100 1
b0 0
b1101 !
b1101 .
b1101 /
04
07
15
0%
b1100 $
b1100 -
b1100 (
b0 *
b1011000 )
b10110 &
b10110 +
#89
1C
1<
1T
0M
1E
1?
1W
0P
0H
1@
16
08
0=
1R
0J
0B
1:
13
1;
b10011 1
b11 0
b10101 !
b10101 .
b10101 /
14
07
15
1%
b1 *
b1011001 )
b1101 &
b1101 +
#90
0S
0L
0O
0K
0C
b1 0
0D
0<
0T
1M
1E
0G
1=
0?
0W
1P
1H
0@
0R
1J
1B
0:
b1101 1
b1110 !
b1110 .
b1110 /
05
0%
b1101 $
b1101 -
b1101 (
b0 *
b1011010 )
b10101 &
b10101 +
#91
1C
b11 0
1<
1T
0M
1E
0=
1?
17
1W
0P
0H
1@
06
18
1R
0J
0B
1:
03
b10010 1
b10100 !
b10100 .
b10100 /
05
1%
b1 *
b1011011 )
b1110 &
b1110 +
#92
0S
0L
0O
0K
0C
0D
0T
1M
1E
0G
0<
0W
1P
1H
0?
1=
0R
1J
1B
0;
b1110 1
b0 0
b1111 !
b1111 .
b1111 /
04
07
15
0%
b1110 $
b1110 -
b1110 (
b0 *
b1011100 )
b10100 &
b10100 +
#93
0C
1T
0M
0E
0<
1W
0P
0H
0@
16
08
0?
1=
1R
0J
0B
0:
13
1;
b10001 1
b1 0
b10011 !
b10011 .
b10011 /
14
07
15
1%
b1 *
b1011101 )
b1111 &
b1111 +
#94
1S
1L
1O
1K
1D
1G
1C
b1111 0
1<
1T
0M
0E
0=
1?
0W
1P
1H
1@
0R
1J
1B
1:
b1111 1
b10000 !
b10000 .
b10000 /
05
0%
b1111 $
b1111 -
b1111 (
b0 *
b1011110 )
b10011 &
b10011 +
#95
0S
0K
0C
b1 0
0"
0L
0D
0<
1T
0V
0M
0O
0E
0G
1=
0?
17
1W
0P
0H
0@
06
18
1R
0J
0B
0:
03
b10000 1
b10010 !
b10010 .
b10010 /
05
1%
b1 *
b1011111 )
b10000 &
b10000 +
#96
0=
0;
b0 0
b10001 !
b10001 .
b10001 /
04
07
15
0%
b10000 $
b10000 -
b10000 (
b0 *
b1100000 )
b10010 &
b10010 +
#97
1S
1L
1O
1K
1D
1G
1C
1<
1T
0M
0E
1?
0W
1P
1H
1@
16
08
0=
0R
1J
1B
1:
13
1;
b1111 1
b1111 0
b10001 !
b10001 .
b10001 /
14
07
15
1%
b1 *
b1100001 )
b10001 &
b10001 +
